Exp10/T3/modules.v
module five_bit(a,b,s,cout);

input [4:0] a,b;
output [4:0] s,c;
output cout;

ha b1(a[0],b[0],s[0],c[1]);
fa b2(a[1],b[1],c[1],s[1],c[2]);
fa b3(a[2],b[2],c[2],s[2],c[3]);
fa b4(a[3],b[3],c[3],s[3],c[4]);
fa b5(a[4],b[4],c[4],s[4],cout);

endmodule

module comp(s,a,out);

input s,a;
output out;

assign out = ~(s ^ a);


endmodule

module ha(a , b, sum , carry);

input a,b;
output sum,carry;

xor x1 (sum , a ,b ) ;
and a1 ( carry , a , b ) ;

endmodule

module fa(a , b , carryin , sum , carryout);

input a,b,carryin;
output sum,carryout;
wire w1,w2,w3;

xor x1 ( w1 , a ,b ) ;
and a1 ( w2 , a , b ) ;
xor x2 ( sum , carryin , w1 );
and a2 ( w3 , w1 , carryin );
or  o3 ( carryout , w2 ,w3 );

endmodule

Exp10/T2/testbench.v
module test_five_bit_adder;                 //test bench module
wire [4:0] s,c;
wire cout;                            //outputs from full adder
reg [4:0] a,b;                        //inputs to the full adder adder module
five_bit DUT(a,b,c,s,cout);           //instantiate the device under test (5 bit adder)
initial
begin
$dumpfile("testfive.vcd");
$dumpvars(0,test_five_bit_adder);
$monitor("At time = %t,a = %b,b = %b,,sum = %b%b",$time,a,b,cout,s);
#10 a = 4'b0000; b = 4'b0000;
#10 a = 4'b0000; b = 4'b0001;
#10 a = 4'b0000; b = 4'b0010;
#10 a = 4'b0000; b = 4'b0011;
#10 a = 4'b0000; b = 4'b0100;
#10 a = 4'b0000; b = 4'b0101;
#10 a = 4'b0000; b = 4'b0110;
#10 a = 4'b0000; b = 4'b0111;
#10 a = 4'b0000; b = 4'b1000;
#10 a = 4'b0000; b = 4'b1001;
#10 a = 4'b0000; b = 4'b1010;
#10 a = 4'b0000; b = 4'b1011;
#10 a = 4'b0000; b = 4'b1100;
#10 a = 4'b0000; b = 4'b1101;
#10 a = 4'b0000; b = 4'b1110;
#10 a = 4'b0000; b = 4'b1111;
#10 a = 4'b0001; b = 4'b0000;
#10 a = 4'b0001; b = 4'b0001;
#10 a = 4'b0001; b = 4'b0010;
#10 a = 4'b0001; b = 4'b0011;
#10 a = 4'b0001; b = 4'b0100;
#10 a = 4'b0001; b = 4'b0101;
#10 a = 4'b0001; b = 4'b0110;
#10 a = 4'b0001; b = 4'b0111;
#10 a = 4'b0001; b = 4'b1000;
#10 a = 4'b0001; b = 4'b1001;
#10 a = 4'b0001; b = 4'b1010;
#10 a = 4'b0001; b = 4'b1011;
#10 a = 4'b0001; b = 4'b1100;
#10 a = 4'b0001; b = 4'b1101;
#10 a = 4'b0001; b = 4'b1110;
#10 a = 4'b0001; b = 4'b1111;
#10 a = 4'b0010; b = 4'b0000;
#10 a = 4'b0010; b = 4'b0001;
#10 a = 4'b0010; b = 4'b0010;
#10 a = 4'b0010; b = 4'b0011;
#10 a = 4'b0010; b = 4'b0100;
#10 a = 4'b0010; b = 4'b0101;
#10 a = 4'b0010; b = 4'b0110;
#10 a = 4'b0010; b = 4'b0111;
#10 a = 4'b0010; b = 4'b1000;
#10 a = 4'b0010; b = 4'b1001;
#10 a = 4'b0010; b = 4'b1010;
#10 a = 4'b0010; b = 4'b1011;
#10 a = 4'b0010; b = 4'b1100;
#10 a = 4'b0010; b = 4'b1101;
#10 a = 4'b0010; b = 4'b1110;
#10 a = 4'b0010; b = 4'b1111;
#10 a = 4'b0011; b = 4'b0000;
#10 a = 4'b0011; b = 4'b0001;
#10 a = 4'b0011; b = 4'b0010;
#10 a = 4'b0011; b = 4'b0011;
#10 a = 4'b0011; b = 4'b0100;
#10 a = 4'b0011; b = 4'b0101;
#10 a = 4'b0011; b = 4'b0110;
#10 a = 4'b0011; b = 4'b0111;
#10 a = 4'b0011; b = 4'b1000;
#10 a = 4'b0011; b = 4'b1001;
#10 a = 4'b0011; b = 4'b1010;
#10 a = 4'b0011; b = 4'b1011;
#10 a = 4'b0011; b = 4'b1100;
#10 a = 4'b0011; b = 4'b1101;
#10 a = 4'b0011; b = 4'b1110;
#10 a = 4'b0011; b = 4'b1111;
#10 a = 4'b0100; b = 4'b0000;
#10 a = 4'b0100; b = 4'b0001;
#10 a = 4'b0100; b = 4'b0010;
#10 a = 4'b0100; b = 4'b0011;
#10 a = 4'b0100; b = 4'b0100;
#10 a = 4'b0100; b = 4'b0101;
#10 a = 4'b0100; b = 4'b0110;
#10 a = 4'b0100; b = 4'b0111;
#10 a = 4'b0100; b = 4'b1000;
#10 a = 4'b0100; b = 4'b1001;
#10 a = 4'b0100; b = 4'b1010;
#10 a = 4'b0100; b = 4'b1011;
#10 a = 4'b0100; b = 4'b1100;
#10 a = 4'b0100; b = 4'b1101;
#10 a = 4'b0100; b = 4'b1110;
#10 a = 4'b0100; b = 4'b1111;
#10 a = 4'b0101; b = 4'b0000;
#10 a = 4'b0101; b = 4'b0001;
#10 a = 4'b0101; b = 4'b0010;
#10 a = 4'b0101; b = 4'b0011;
#10 a = 4'b0101; b = 4'b0100;
#10 a = 4'b0101; b = 4'b0101;
#10 a = 4'b0101; b = 4'b0110;
#10 a = 4'b0101; b = 4'b0111;
#10 a = 4'b0101; b = 4'b1000;
#10 a = 4'b0101; b = 4'b1001;
#10 a = 4'b0101; b = 4'b1010;
#10 a = 4'b0101; b = 4'b1011;
#10 a = 4'b0101; b = 4'b1100;
#10 a = 4'b0101; b = 4'b1101;
#10 a = 4'b0101; b = 4'b1110;
#10 a = 4'b0101; b = 4'b1111;
#10 a = 4'b0110; b = 4'b0000;
#10 a = 4'b0110; b = 4'b0001;
#10 a = 4'b0110; b = 4'b0010;
#10 a = 4'b0110; b = 4'b0011;
#10 a = 4'b0110; b = 4'b0100;
#10 a = 4'b0110; b = 4'b0101;
#10 a = 4'b0110; b = 4'b0110;
#10 a = 4'b0110; b = 4'b0111;
#10 a = 4'b0110; b = 4'b1000;
#10 a = 4'b0110; b = 4'b1001;
#10 a = 4'b0110; b = 4'b1010;
#10 a = 4'b0110; b = 4'b1011;
#10 a = 4'b0110; b = 4'b1100;
#10 a = 4'b0110; b = 4'b1101;
#10 a = 4'b0110; b = 4'b1110;
#10 a = 4'b0110; b = 4'b1111;
#10 a = 4'b0111; b = 4'b0000;
#10 a = 4'b0111; b = 4'b0001;
#10 a = 4'b0111; b = 4'b0010;
#10 a = 4'b0111; b = 4'b0011;
#10 a = 4'b0111; b = 4'b0100;
#10 a = 4'b0111; b = 4'b0101;
#10 a = 4'b0111; b = 4'b0110;
#10 a = 4'b0111; b = 4'b0111;
#10 a = 4'b0111; b = 4'b1000;
#10 a = 4'b0111; b = 4'b1001;
#10 a = 4'b0111; b = 4'b1010;
#10 a = 4'b0111; b = 4'b1011;
#10 a = 4'b0111; b = 4'b1100;
#10 a = 4'b0111; b = 4'b1101;
#10 a = 4'b0111; b = 4'b1110;
#10 a = 4'b0111; b = 4'b1111;
#10 a = 4'b1000; b = 4'b0000;
#10 a = 4'b1000; b = 4'b0001;
#10 a = 4'b1000; b = 4'b0010;
#10 a = 4'b1000; b = 4'b0011;
#10 a = 4'b1000; b = 4'b0100;
#10 a = 4'b1000; b = 4'b0101;
#10 a = 4'b1000; b = 4'b0110;
#10 a = 4'b1000; b = 4'b0111;
#10 a = 4'b1000; b = 4'b1000;
#10 a = 4'b1000; b = 4'b1001;
#10 a = 4'b1000; b = 4'b1010;
#10 a = 4'b1000; b = 4'b1011;
#10 a = 4'b1000; b = 4'b1100;
#10 a = 4'b1000; b = 4'b1101;
#10 a = 4'b1000; b = 4'b1110;
#10 a = 4'b1000; b = 4'b1111;
#10 a = 4'b1001; b = 4'b0000;
#10 a = 4'b1001; b = 4'b0001;
#10 a = 4'b1001; b = 4'b0010;
#10 a = 4'b1001; b = 4'b0011;
#10 a = 4'b1001; b = 4'b0100;
#10 a = 4'b1001; b = 4'b0101;
#10 a = 4'b1001; b = 4'b0110;
#10 a = 4'b1001; b = 4'b0111;
#10 a = 4'b1001; b = 4'b1000;
#10 a = 4'b1001; b = 4'b1001;
#10 a = 4'b1001; b = 4'b1010;
#10 a = 4'b1001; b = 4'b1011;
#10 a = 4'b1001; b = 4'b1100;
#10 a = 4'b1001; b = 4'b1101;
#10 a = 4'b1001; b = 4'b1110;
#10 a = 4'b1001; b = 4'b1111;
#10 a = 4'b1010; b = 4'b0000;
#10 a = 4'b1010; b = 4'b0001;
#10 a = 4'b1010; b = 4'b0010;
#10 a = 4'b1010; b = 4'b0011;
#10 a = 4'b1010; b = 4'b0100;
#10 a = 4'b1010; b = 4'b0101;
#10 a = 4'b1010; b = 4'b0110;
#10 a = 4'b1010; b = 4'b0111;
#10 a = 4'b1010; b = 4'b1000;
#10 a = 4'b1010; b = 4'b1001;
#10 a = 4'b1010; b = 4'b1010;
#10 a = 4'b1010; b = 4'b1011;
#10 a = 4'b1010; b = 4'b1100;
#10 a = 4'b1010; b = 4'b1101;
#10 a = 4'b1010; b = 4'b1110;
#10 a = 4'b1010; b = 4'b1111;
#10 a = 4'b1011; b = 4'b0000;
#10 a = 4'b1011; b = 4'b0001;
#10 a = 4'b1011; b = 4'b0010;
#10 a = 4'b1011; b = 4'b0011;
#10 a = 4'b1011; b = 4'b0100;
#10 a = 4'b1011; b = 4'b0101;
#10 a = 4'b1011; b = 4'b0110;
#10 a = 4'b1011; b = 4'b0111;
#10 a = 4'b1011; b = 4'b1000;
#10 a = 4'b1011; b = 4'b1001;
#10 a = 4'b1011; b = 4'b1010;
#10 a = 4'b1011; b = 4'b1011;
#10 a = 4'b1011; b = 4'b1100;
#10 a = 4'b1011; b = 4'b1101;
#10 a = 4'b1011; b = 4'b1110;
#10 a = 4'b1011; b = 4'b1111;
#10 a = 4'b1100; b = 4'b0000;
#10 a = 4'b1100; b = 4'b0001;
#10 a = 4'b1100; b = 4'b0010;
#10 a = 4'b1100; b = 4'b0011;
#10 a = 4'b1100; b = 4'b0100;
#10 a = 4'b1100; b = 4'b0101;
#10 a = 4'b1100; b = 4'b0110;
#10 a = 4'b1100; b = 4'b0111;
#10 a = 4'b1100; b = 4'b1000;
#10 a = 4'b1100; b = 4'b1001;
#10 a = 4'b1100; b = 4'b1010;
#10 a = 4'b1100; b = 4'b1011;
#10 a = 4'b1100; b = 4'b1100;
#10 a = 4'b1100; b = 4'b1101;
#10 a = 4'b1100; b = 4'b1110;
#10 a = 4'b1100; b = 4'b1111;
#10 a = 4'b1101; b = 4'b0000;
#10 a = 4'b1101; b = 4'b0001;
#10 a = 4'b1101; b = 4'b0010;
#10 a = 4'b1101; b = 4'b0011;
#10 a = 4'b1101; b = 4'b0100;
#10 a = 4'b1101; b = 4'b0101;
#10 a = 4'b1101; b = 4'b0110;
#10 a = 4'b1101; b = 4'b0111;
#10 a = 4'b1101; b = 4'b1000;
#10 a = 4'b1101; b = 4'b1001;
#10 a = 4'b1101; b = 4'b1010;
#10 a = 4'b1101; b = 4'b1011;
#10 a = 4'b1101; b = 4'b1100;
#10 a = 4'b1101; b = 4'b1101;
#10 a = 4'b1101; b = 4'b1110;
#10 a = 4'b1101; b = 4'b1111;
#10 a = 4'b1110; b = 4'b0000;
#10 a = 4'b1110; b = 4'b0001;
#10 a = 4'b1110; b = 4'b0010;
#10 a = 4'b1110; b = 4'b0011;
#10 a = 4'b1110; b = 4'b0100;
#10 a = 4'b1110; b = 4'b0101;
#10 a = 4'b1110; b = 4'b0110;
#10 a = 4'b1110; b = 4'b0111;
#10 a = 4'b1110; b = 4'b1000;
#10 a = 4'b1110; b = 4'b1001;
#10 a = 4'b1110; b = 4'b1010;
#10 a = 4'b1110; b = 4'b1011;
#10 a = 4'b1110; b = 4'b1100;
#10 a = 4'b1110; b = 4'b1101;
#10 a = 4'b1110; b = 4'b1110;
#10 a = 4'b1110; b = 4'b1111;
#10 a = 4'b1111; b = 4'b0000;
#10 a = 4'b1111; b = 4'b0001;
#10 a = 4'b1111; b = 4'b0010;
#10 a = 4'b1111; b = 4'b0011;
#10 a = 4'b1111; b = 4'b0100;
#10 a = 4'b1111; b = 4'b0101;
#10 a = 4'b1111; b = 4'b0110;
#10 a = 4'b1111; b = 4'b0111;
#10 a = 4'b1111; b = 4'b1000;
#10 a = 4'b1111; b = 4'b1001;
#10 a = 4'b1111; b = 4'b1010;
#10 a = 4'b1111; b = 4'b1011;
#10 a = 4'b1111; b = 4'b1100;
#10 a = 4'b1111; b = 4'b1101;
#10 a = 4'b1111; b = 4'b1110;
#10 a = 4'b1111; b = 4'b1111;

#10 $finish;
end
endmodule

Exp10/T2/testfive.vcd
$date
	Tue Jan 29 15:59:50 2019
$end
$version
	Icarus Verilog
$end
$timescale
	1s
$end
$scope module test_five_bit_adder $end
$var wire 5 ! s [4:0] $end
$var wire 1 " cout $end
$var wire 5 # c [4:0] $end
$var reg 5 $ a [4:0] $end
$var reg 5 % b [4:0] $end
$scope module DUT $end
$var wire 5 & a [4:0] $end
$var wire 5 ' b [4:0] $end
$var wire 5 ( s [4:0] $end
$var wire 1 " cout $end
$var wire 5 ) c [4:0] $end
$scope module b1 $end
$var wire 1 * a $end
$var wire 1 + b $end
$var wire 1 , carry $end
$var wire 1 - sum $end
$upscope $end
$scope module b2 $end
$var wire 1 . a $end
$var wire 1 / b $end
$var wire 1 0 carryin $end
$var wire 1 1 carryout $end
$var wire 1 2 sum $end
$var wire 1 3 w1 $end
$var wire 1 4 w2 $end
$var wire 1 5 w3 $end
$upscope $end
$scope module b3 $end
$var wire 1 6 a $end
$var wire 1 7 b $end
$var wire 1 8 carryin $end
$var wire 1 9 carryout $end
$var wire 1 : sum $end
$var wire 1 ; w1 $end
$var wire 1 < w2 $end
$var wire 1 = w3 $end
$upscope $end
$scope module b4 $end
$var wire 1 > a $end
$var wire 1 ? b $end
$var wire 1 @ carryin $end
$var wire 1 A carryout $end
$var wire 1 B sum $end
$var wire 1 C w1 $end
$var wire 1 D w2 $end
$var wire 1 E w3 $end
$upscope $end
$scope module b5 $end
$var wire 1 F a $end
$var wire 1 G b $end
$var wire 1 H carryin $end
$var wire 1 " carryout $end
$var wire 1 I sum $end
$var wire 1 J w1 $end
$var wire 1 K w2 $end
$var wire 1 L w3 $end
$upscope $end
$upscope $end
$upscope $end
$enddefinitions $end
#0
$dumpvars
xL
xK
xJ
xI
xH
xG
xF
xE
xD
xC
xB
xA
x@
x?
x>
x=
x<
x;
x:
x9
x8
x7
x6
x5
x4
x3
x2
x1
x0
x/
x.
x-
x,
x+
x*
bxz )
bx (
bx '
bx &
bx %
bx $
bxz #
x"
bx !
$end
#10
0:
0B
0I
08
0@
0H
02
01
09
0A
0"
00
05
0=
0E
0L
b0 !
b0 (
0-
b0z #
b0z )
0,
03
04
0;
0<
0C
0D
0J
0K
0+
0/
07
0?
0G
0*
0.
06
0>
0F
b0 %
b0 '
b0 $
b0 &
#20
b1 !
b1 (
1-
1+
b1 %
b1 '
#30
12
b10 !
b10 (
0-
13
0+
1/
b10 %
b10 '
#40
b11 !
b11 (
1-
1+
b11 %
b11 '
#50
02
1:
b100 !
b100 (
0-
03
1;
0+
0/
17
b100 %
b100 '
#60
b101 !
b101 (
1-
1+
b101 %
b101 '
#70
12
b110 !
b110 (
0-
13
0+
1/
b110 %
b110 '
#80
b111 !
b111 (
1-
1+
b111 %
b111 '
#90
02
0:
1B
b1000 !
b1000 (
0-
03
0;
1C
0+
0/
07
1?
b1000 %
b1000 '
#100
b1001 !
b1001 (
1-
1+
b1001 %
b1001 '
#110
12
b1010 !
b1010 (
0-
13
0+
1/
b1010 %
b1010 '
#120
b1011 !
b1011 (
1-
1+
b1011 %
b1011 '
#130
02
1:
b1100 !
b1100 (
0-
03
1;
0+
0/
17
b1100 %
b1100 '
#140
b1101 !
b1101 (
1-
1+
b1101 %
b1101 '
#150
12
b1110 !
b1110 (
0-
13
0+
1/
b1110 %
b1110 '
#160
b1111 !
b1111 (
1-
1+
b1111 %
b1111 '
#170
02
0:
b1 !
b1 (
0B
03
0;
0C
0+
0/
07
0?
1*
b0 %
b0 '
b1 $
b1 &
#180
12
10
b10 !
b10 (
0-
b1z #
b1z )
1,
1+
b1 %
b1 '
#190
0:
08
01
00
12
05
b11 !
b11 (
1-
b0z #
b0z )
0,
13
0+
1/
b10 %
b10 '
#200
1:
18
11
02
15
10
b100 !
b100 (
0-
b11z #
b11z )
1,
1+
b11 %
b11 '
#210
0B
08
0@
01
09
00
02
05
1:
0=
b101 !
b101 (
1-
b0z #
b0z )
0,
03
1;
0+
0/
17
b100 %
b100 '
#220
12
10
b110 !
b110 (
0-
b1z #
b1z )
1,
1+
b101 %
b101 '
#230
0B
0@
09
1:
0=
08
01
00
12
05
b111 !
b111 (
1-
b0z #
b0z )
0,
13
0+
1/
b110 %
b110 '
#240
1B
1@
19
0:
1=
18
11
02
15
10
b1000 !
b1000 (
0-
b111z #
b111z )
1,
1+
b111 %
b111 '
#250
0I
08
0@
0H
01
09
0A
00
02
05
0:
0=
1B
0E
b1001 !
b1001 (
1-
b0z #
b0z )
0,
03
0;
1C
0+
0/
07
1?
b1000 %
b1000 '
#260
12
10
b1010 !
b1010 (
0-
b1z #
b1z )
1,
1+
b1001 %
b1001 '
#270
0:
08
01
00
12
05
b1011 !
b1011 (
1-
b0z #
b0z )
0,
13
0+
1/
b1010 %
b1010 '
#280
1:
18
11
02
15
10
b1100 !
b1100 (
0-
b11z #
b11z )
1,
1+
b1011 %
b1011 '
#290
0I
0H
0A
1B
0E
08
0@
01
09
00
02
05
1:
0=
b1101 !
b1101 (
1-
b0z #
b0z )
0,
03
1;
0+
0/
17
b1100 %
b1100 '
#300
12
10
b1110 !
b1110 (
0-
b1z #
b1z )
1,
1+
b1101 %
b1101 '
#310
0I
0H
0A
1B
0E
0@
09
1:
0=
08
01
00
12
05
b1111 !
b1111 (
1-
b0z #
b0z )
0,
13
0+
1/
b1110 %
b1110 '
#320
1I
1H
1A
0B
1E
1@
19
0:
1=
18
11
02
15
10
b10000 !
b10000 (
0-
b1111z #
b1111z )
1,
1+
b1111 %
b1111 '
#330
0I
08
0@
0H
01
09
0A
12
05
0:
0=
b10 !
b10 (
0B
0E
00
0;
0C
b0z #
b0z )
0,
0+
0/
07
0?
0*
1.
b0 %
b0 '
b10 $
b10 &
#340
b11 !
b11 (
1-
1+
b1 %
b1 '
#350
1:
18
02
b10z #
b10z )
11
b100 !
b100 (
0-
03
14
0+
1/
b10 %
b10 '
#360
b101 !
b101 (
1-
1+
b11 %
b11 '
#370
0B
0@
08
09
12
b0z #
b0z )
01
1:
0=
b110 !
b110 (
0-
13
04
1;
0+
0/
17
b100 %
b100 '
#380
b111 !
b111 (
1-
1+
b101 %
b101 '
#390
1B
1@
19
0:
1=
18
02
b110z #
b110z )
11
b1000 !
b1000 (
0-
03
14
0+
1/
b110 %
b110 '
#400
b1001 !
b1001 (
1-
1+
b111 %
b111 '
#410
0I
0@
0H
08
09
0A
12
b0z #
b0z )
01
0:
0=
1B
0E
b1010 !
b1010 (
0-
13
04
0;
1C
0+
0/
07
1?
b1000 %
b1000 '
#420
b1011 !
b1011 (
1-
1+
b1001 %
b1001 '
#430
1:
18
02
b10z #
b10z )
11
b1100 !
b1100 (
0-
03
14
0+
1/
b1010 %
b1010 '
#440
b1101 !
b1101 (
1-
1+
b1011 %
b1011 '
#450
0I
0H
0A
1B
0E
0@
08
09
12
b0z #
b0z )
01
1:
0=
b1110 !
b1110 (
0-
13
04
1;
0+
0/
17
b1100 %
b1100 '
#460
b1111 !
b1111 (
1-
1+
b1101 %
b1101 '
#470
1I
1H
1A
0B
1E
1@
19
0:
1=
18
02
b1110z #
b1110z )
11
b10000 !
b10000 (
0-
03
14
0+
1/
b1110 %
b1110 '
#480
b10001 !
b10001 (
1-
1+
b1111 %
b1111 '
#490
0I
0@
0H
08
09
0A
12
b0z #
b0z )
01
0:
0=
b11 !
b11 (
0B
0E
13
04
0;
0C
0+
0/
07
0?
1*
b0 %
b0 '
b11 $
b11 &
#500
1:
18
11
02
15
10
b100 !
b100 (
0-
b11z #
b11z )
1,
1+
b1 %
b1 '
#510
00
02
05
b101 !
b101 (
1-
b10z #
b10z )
0,
03
14
0+
1/
b10 %
b10 '
#520
12
10
b110 !
b110 (
0-
b11z #
b11z )
1,
1+
b11 %
b11 '
#530
0B
0@
08
09
00
12
05
01
1:
0=
b111 !
b111 (
1-
b0z #
b0z )
0,
13
04
1;
0+
0/
17
b100 %
b100 '
#540
1B
1@
19
0:
1=
18
11
02
15
10
b1000 !
b1000 (
0-
b111z #
b111z )
1,
1+
b101 %
b101 '
#550
00
02
05
b1001 !
b1001 (
1-
b110z #
b110z )
0,
03
14
0+
1/
b110 %
b110 '
#560
12
10
b1010 !
b1010 (
0-
b111z #
b111z )
1,
1+
b111 %
b111 '
#570
0I
0@
0H
08
09
0A
00
12
05
01
0:
0=
1B
0E
b1011 !
b1011 (
1-
b0z #
b0z )
0,
13
04
0;
1C
0+
0/
07
1?
b1000 %
b1000 '
#580
1:
18
11
02
15
10
b1100 !
b1100 (
0-
b11z #
b11z )
1,
1+
b1001 %
b1001 '
#590
00
02
05
b1101 !
b1101 (
1-
b10z #
b10z )
0,
03
14
0+
1/
b1010 %
b1010 '
#600
12
10
b1110 !
b1110 (
0-
b11z #
b11z )
1,
1+
b1011 %
b1011 '
#610
0I
0H
0A
1B
0E
0@
08
09
00
12
05
01
1:
0=
b1111 !
b1111 (
1-
b0z #
b0z )
0,
13
04
1;
0+
0/
17
b1100 %
b1100 '
#620
1I
1H
1A
0B
1E
1@
19
0:
1=
18
11
02
15
10
b10000 !
b10000 (
0-
b1111z #
b1111z )
1,
1+
b1101 %
b1101 '
#630
00
02
05
b10001 !
b10001 (
1-
b1110z #
b1110z )
0,
03
14
0+
1/
b1110 %
b1110 '
#640
12
10
b10010 !
b10010 (
0-
b1111z #
b1111z )
1,
1+
b1111 %
b1111 '
#650
0@
0I
09
0H
1:
0=
0A
02
08
b100 !
b100 (
0B
0E
00
01
0C
b0z #
b0z )
0,
04
0+
0/
07
0?
0*
0.
16
b0 %
b0 '
b100 $
b100 &
#660
b101 !
b101 (
1-
1+
b1 %
b1 '
#670
12
b110 !
b110 (
0-
13
0+
1/
b10 %
b10 '
#680
b111 !
b111 (
1-
1+
b11 %
b11 '
#690
1B
1@
02
0:
b100z #
b100z )
19
b1000 !
b1000 (
0-
03
0;
1<
0+
0/
17
b100 %
b100 '
#700
b1001 !
b1001 (
1-
1+
b101 %
b101 '
#710
12
b1010 !
b1010 (
0-
13
0+
1/
b110 %
b110 '
#720
b1011 !
b1011 (
1-
1+
b111 %
b111 '
#730
0I
0H
0@
0A
02
1:
b0z #
b0z )
09
1B
0E
b1100 !
b1100 (
0-
03
1;
0<
1C
0+
0/
07
1?
b1000 %
b1000 '
#740
b1101 !
b1101 (
1-
1+
b1001 %
b1001 '
#750
12
b1110 !
b1110 (
0-
13
0+
1/
b1010 %
b1010 '
#760
b1111 !
b1111 (
1-
1+
b1011 %
b1011 '
#770
1I
1H
1A
0B
1E
1@
02
0:
b1100z #
b1100z )
19
b10000 !
b10000 (
0-
03
0;
1<
0+
0/
17
b1100 %
b1100 '
#780
b10001 !
b10001 (
1-
1+
b1101 %
b1101 '
#790
12
b10010 !
b10010 (
0-
13
0+
1/
b1110 %
b1110 '
#800
b10011 !
b10011 (
1-
1+
b1111 %
b1111 '
#810
0I
0H
0@
0A
02
1:
b0z #
b0z )
09
b101 !
b101 (
0B
0E
03
1;
0<
0C
0+
0/
07
0?
1*
b0 %
b0 '
b101 $
b101 &
#820
12
10
b110 !
b110 (
0-
b1z #
b1z )
1,
1+
b1 %
b1 '
#830
0B
0@
09
1:
0=
08
01
00
12
05
b111 !
b111 (
1-
b0z #
b0z )
0,
13
0+
1/
b10 %
b10 '
#840
1B
1@
19
0:
1=
18
11
02
15
10
b1000 !
b1000 (
0-
b111z #
b111z )
1,
1+
b11 %
b11 '
#850
08
01
00
02
05
0:
0=
b1001 !
b1001 (
1-
b100z #
b100z )
0,
03
0;
1<
0+
0/
17
b100 %
b100 '
#860
12
10
b1010 !
b1010 (
0-
b101z #
b101z )
1,
1+
b101 %
b101 '
#870
0:
08
01
00
12
05
b1011 !
b1011 (
1-
b100z #
b100z )
0,
13
0+
1/
b110 %
b110 '
#880
1:
18
11
02
15
10
b1100 !
b1100 (
0-
b111z #
b111z )
1,
1+
b111 %
b111 '
#890
0I
08
0H
01
0@
0A
00
02
05
1:
0=
09
1B
0E
b1101 !
b1101 (
1-
b0z #
b0z )
0,
03
1;
0<
1C
0+
0/
07
1?
b1000 %
b1000 '
#900
12
10
b1110 !
b1110 (
0-
b1z #
b1z )
1,
1+
b1001 %
b1001 '
#910
0I
0H
0A
1B
0E
0@
09
1:
0=
08
01
00
12
05
b1111 !
b1111 (
1-
b0z #
b0z )
0,
13
0+
1/
b1010 %
b1010 '
#920
1I
1H
1A
0B
1E
1@
19
0:
1=
18
11
02
15
10
b10000 !
b10000 (
0-
b1111z #
b1111z )
1,
1+
b1011 %
b1011 '
#930
08
01
00
02
05
0:
0=
b10001 !
b10001 (
1-
b1100z #
b1100z )
0,
03
0;
1<
0+
0/
17
b1100 %
b1100 '
#940
12
10
b10010 !
b10010 (
0-
b1101z #
b1101z )
1,
1+
b1101 %
b1101 '
#950
0:
08
01
00
12
05
b10011 !
b10011 (
1-
b1100z #
b1100z )
0,
13
0+
1/
b1110 %
b1110 '
#960
1:
18
11
02
15
10
b10100 !
b10100 (
0-
b1111z #
b1111z )
1,
1+
b1111 %
b1111 '
#970
0I
08
0H
01
0@
0A
12
05
1:
0=
09
b110 !
b110 (
0B
0E
00
1;
0<
0C
b0z #
b0z )
0,
0+
0/
07
0?
0*
1.
b0 %
b0 '
b110 $
b110 &
#980
b111 !
b111 (
1-
1+
b1 %
b1 '
#990
1B
1@
19
0:
1=
18
02
b110z #
b110z )
11
b1000 !
b1000 (
0-
03
14
0+
1/
b10 %
b10 '
#1000
b1001 !
b1001 (
1-
1+
b11 %
b11 '
#1010
08
12
b100z #
b100z )
01
0:
0=
b1010 !
b1010 (
0-
13
04
0;
1<
0+
0/
17
b100 %
b100 '
#1020
b1011 !
b1011 (
1-
1+
b101 %
b101 '
#1030
1:
18
02
b110z #
b110z )
11
b1100 !
b1100 (
0-
03
14
0+
1/
b110 %
b110 '
#1040
b1101 !
b1101 (
1-
1+
b111 %
b111 '
#1050
0I
0H
08
0@
0A
12
01
1:
0=
b0z #
b0z )
09
1B
0E
b1110 !
b1110 (
0-
13
04
1;
0<
1C
0+
0/
07
1?
b1000 %
b1000 '
#1060
b1111 !
b1111 (
1-
1+
b1001 %
b1001 '
#1070
1I
1H
1A
0B
1E
1@
19
0:
1=
18
02
b1110z #
b1110z )
11
b10000 !
b10000 (
0-
03
14
0+
1/
b1010 %
b1010 '
#1080
b10001 !
b10001 (
1-
1+
b1011 %
b1011 '
#1090
08
12
b1100z #
b1100z )
01
0:
0=
b10010 !
b10010 (
0-
13
04
0;
1<
0+
0/
17
b1100 %
b1100 '
#1100
b10011 !
b10011 (
1-
1+
b1101 %
b1101 '
#1110
1:
18
02
b1110z #
b1110z )
11
b10100 !
b10100 (
0-
03
14
0+
1/
b1110 %
b1110 '
#1120
b10101 !
b10101 (
1-
1+
b1111 %
b1111 '
#1130
0I
0H
08
0@
0A
12
01
1:
0=
b0z #
b0z )
09
b111 !
b111 (
0B
0E
13
04
1;
0<
0C
0+
0/
07
0?
1*
b0 %
b0 '
b111 $
b111 &
#1140
1B
1@
19
0:
1=
18
11
02
15
10
b1000 !
b1000 (
0-
b111z #
b111z )
1,
1+
b1 %
b1 '
#1150
00
02
05
b1001 !
b1001 (
1-
b110z #
b110z )
0,
03
14
0+
1/
b10 %
b10 '
#1160
12
10
b1010 !
b1010 (
0-
b111z #
b111z )
1,
1+
b11 %
b11 '
#1170
08
00
12
05
01
0:
0=
b1011 !
b1011 (
1-
b100z #
b100z )
0,
13
04
0;
1<
0+
0/
17
b100 %
b100 '
#1180
1:
18
11
02
15
10
b1100 !
b1100 (
0-
b111z #
b111z )
1,
1+
b101 %
b101 '
#1190
00
02
05
b1101 !
b1101 (
1-
b110z #
b110z )
0,
03
14
0+
1/
b110 %
b110 '
#1200
12
10
b1110 !
b1110 (
0-
b111z #
b111z )
1,
1+
b111 %
b111 '
#1210
0I
0H
08
0@
0A
00
12
05
01
1:
0=
09
1B
0E
b1111 !
b1111 (
1-
b0z #
b0z )
0,
13
04
1;
0<
1C
0+
0/
07
1?
b1000 %
b1000 '
#1220
1I
1H
1A
0B
1E
1@
19
0:
1=
18
11
02
15
10
b10000 !
b10000 (
0-
b1111z #
b1111z )
1,
1+
b1001 %
b1001 '
#1230
00
02
05
b10001 !
b10001 (
1-
b1110z #
b1110z )
0,
03
14
0+
1/
b1010 %
b1010 '
#1240
12
10
b10010 !
b10010 (
0-
b1111z #
b1111z )
1,
1+
b1011 %
b1011 '
#1250
08
00
12
05
01
0:
0=
b10011 !
b10011 (
1-
b1100z #
b1100z )
0,
13
04
0;
1<
0+
0/
17
b1100 %
b1100 '
#1260
1:
18
11
02
15
10
b10100 !
b10100 (
0-
b1111z #
b1111z )
1,
1+
b1101 %
b1101 '
#1270
00
02
05
b10101 !
b10101 (
1-
b1110z #
b1110z )
0,
03
14
0+
1/
b1110 %
b1110 '
#1280
12
10
b10110 !
b10110 (
0-
b1111z #
b1111z )
1,
1+
b1111 %
b1111 '
#1290
0I
0H
0A
0:
1B
0E
b1000 !
b1000 (
02
08
0@
00
01
09
b0z #
b0z )
0,
04
0<
0+
0/
07
0?
0*
0.
06
1>
b0 %
b0 '
b1000 $
b1000 &
#1300
b1001 !
b1001 (
1-
1+
b1 %
b1 '
