mod.v
module max(a,b,out);
input [3:0] a,b;
reg [3:0] wi;
output [3:0] out;
always@(a or b or wi)
begin
if(a>b)
  wi=a;
else if (b>a)
  wi=b;
end

assign out = wi;

endmodule

Exp11/T4/testbench.v
module test_max;             //test bench module
reg [3:0] a,b;
output [3:0] out;
max DUT(a,b,out);
initial
begin
$dumpfile("test.vcd");
$dumpvars(0,test_max);
$monitor("At time = %t , A = %b , B = %b , Max(A,B) = %b",$time,a,b,out);
#10 a = 4'b0000; b = 4'b0110;
#10 a = 4'b0000; b = 4'b0111;
#10 a = 4'b0100; b = 4'b1000;
#10 a = 4'b0000; b = 4'b1001;
#10 a = 4'b1100; b = 4'b1010;
#10 a = 4'b0000; b = 4'b1011;
#10 a = 4'b1010; b = 4'b1100;
#10 a = 4'b0000; b = 4'b1101;
#10 a = 4'b1000; b = 4'b1110;
#10 a = 4'b0000; b = 4'b1111;
#10 a = 4'b1001; b = 4'b0000;
#10 a = 4'b0001; b = 4'b0001;
#10 a = 4'b0001; b = 4'b0010;
#10 a = 4'b1001; b = 4'b0011;
#10 a = 4'b0001; b = 4'b0100;
#10 a = 4'b0001; b = 4'b0101;
#10 a = 4'b0001; b = 4'b0110;
#10 a = 4'b1001; b = 4'b0111;
#10 a = 4'b0001; b = 4'b1000;
$finish;
end
endmodule

Exp11/T4/test.vcd
$date
	Mon Feb  4 16:50:13 2019
$end
$version
	Icarus Verilog
$end
$timescale
	1s
$end
$scope module test_max $end
$var wire 4 ! out [3:0] $end
$var reg 4 " a [3:0] $end
$var reg 4 # b [3:0] $end
$scope module DUT $end
$var wire 4 $ a [3:0] $end
$var wire 4 % b [3:0] $end
$var wire 4 & out [3:0] $end
$var reg 4 ' wi [3:0] $end
$upscope $end
$upscope $end
$enddefinitions $end
#0
$dumpvars
bx '
bx &
bx %
bx $
bx #
bx "
bx !
$end
#10
b110 !
b110 &
b110 '
b110 #
b110 %
b0 "
b0 $
#20
b111 !
b111 &
b111 '
b111 #
b111 %
#30
b1000 !
b1000 &
b1000 '
b1000 #
b1000 %
b100 "
b100 $
#40
b1001 !
b1001 &
b1001 '
b1001 #
b1001 %
b0 "
b0 $
#50
b1100 !
b1100 &
b1100 '
b1010 #
b1010 %
b1100 "
b1100 $
#60
b1011 !
b1011 &
b1011 '
b1011 #
b1011 %
b0 "
b0 $
#70
b1100 !
b1100 &
b1100 '
b1100 #
b1100 %
b1010 "
b1010 $
#80
b1101 !
b1101 &
b1101 '
b1101 #
b1101 %
b0 "
b0 $
#90
b1110 !
b1110 &
b1110 '
b1110 #
b1110 %
b1000 "
b1000 $
#100
b1111 !
b1111 &
b1111 '
b1111 #
b1111 %
b0 "
b0 $
#110
b1001 !
b1001 &
b1001 '
b0 #
b0 %
b1001 "
b1001 $
#120
b1 #
b1 %
b1 "
b1 $
#130
b10 !
b10 &
b10 '
b10 #
b10 %
#140
b1001 !
b1001 &
b1001 '
b11 #
b11 %
b1001 "
b1001 $
#150
b100 !
b100 &
b100 '
b100 #
b100 %
b1 "
b1 $
#160
b101 !
b101 &
b101 '
b101 #
b101 %
#170
b110 !
b110 &
b110 '
b110 #
b110 %
#180
b1001 !
b1001 &
b1001 '
b111 #
b111 %
b1001 "
b1001 $
#190
b1000 !
b1000 &
b1000 '
b1000 #
b1000 %
b1 "
b1 $
