Exp10/T3/modules.v
module five_bit(a,b,s,cout);

input [4:0] a,b;
output [4:0] s,c;
output cout;

ha b1(a[0],b[0],s[0],c[1]);
fa b2(a[1],b[1],c[1],s[1],c[2]);
fa b3(a[2],b[2],c[2],s[2],c[3]);
fa b4(a[3],b[3],c[3],s[3],c[4]);
fa b5(a[4],b[4],c[4],s[4],cout);

endmodule

module comp(s,a,out);

input s,a;
output out;

assign out = ~(s ^ a);


endmodule

module ha(a , b, sum , carry);

input a,b;
output sum,carry;

xor x1 (sum , a ,b ) ;
and a1 ( carry , a , b ) ;

endmodule

module fa(a , b , carryin , sum , carryout);

input a,b,carryin;
output sum,carryout;
wire w1,w2,w3;

xor x1 ( w1 , a ,b ) ;
and a1 ( w2 , a , b ) ;
xor x2 ( sum , carryin , w1 );
and a2 ( w3 , w1 , carryin );
or  o3 ( carryout , w2 ,w3 );

endmodule

Exp10/T3/exp.v
module t3(a,b,s,sum2,cout);

input [3:0] a,b;
input s;
wire [4:0] c,d,tmp;
output [4:0] sum,sum2;
output cout;

comp s0(s,b[0],c[0]);
comp s1(s,b[1],c[1]);
comp s2(s,b[2],c[2]);
comp s3(s,b[3],c[3]);
assign c[4] = c[3];

assign tmp[0]=~s;
assign tmp[1]=0;
assign tmp[2]=0;
assign tmp[3]=0;
assign tmp[4]=0;

assign d[0]=a[0];
assign d[1]=a[1];
assign d[2]=a[2];
assign d[3]=a[3];
assign d[4]=a[3];

five_bit fb1(c,tmp,sum,cout);

five_bit fb2(sum,d,sum2,cout);


endmodule

Exp10/T3/test02.v
module test_four_bit_adder;                 //test bench module                            //outputs from full adder
reg [3:0] a,b;
reg s;
wire [4:0]sum2;
wire cout;                    //inputs to the full adder adder module
t3 DUT(a,b,s,sum2,cout);           //instantiate the device under test (5 bit adder)
initial
begin
$dumpfile("testfive.vcd");
$dumpvars(0,test_four_bit_adder);
$monitor("At time = %t,a = %b,b = %b,s = %b,output= %b",$time,a,b,s,sum2);
#10 a = 4'b0000; b = 4'b0000; s = 1'b0;
#10 a = 4'b0000; b = 4'b0001; s = 1'b0;
#10 a = 4'b0000; b = 4'b0010; s = 1'b0;
#10 a = 4'b1111; b = 4'b0111; s = 1'b1;
#10 a = 4'b1111; b = 4'b1000; s = 1'b1;
#10 a = 4'b1111; b = 4'b1001; s = 1'b1;
#10 a = 4'b1111; b = 4'b1010; s = 1'b1;
#10 a = 4'b1111; b = 4'b1011; s = 1'b1;
#10 a = 4'b1111; b = 4'b1100; s = 1'b1;
#10 a = 4'b1111; b = 4'b1101; s = 1'b1;
#10 a = 4'b1111; b = 4'b1110; s = 1'b1;
#10 a = 4'b1111; b = 4'b1111; s = 1'b1;

#10 $finish;
end
endmodule

Exp10/T3/testfive.vcd
$date
	Tue Jan 29 16:18:52 2019
$end
$version
	Icarus Verilog
$end
$timescale
	1s
$end
$scope module test_four_bit_adder $end
$var wire 1 ! cout $end
$var wire 5 " sum2 [4:0] $end
$var reg 4 # a [3:0] $end
$var reg 4 $ b [3:0] $end
$var reg 1 % s $end
$scope module DUT $end
$var wire 4 & a [3:0] $end
$var wire 4 ' b [3:0] $end
$var wire 5 ( c [4:0] $end
$var wire 1 ! cout $end
$var wire 1 % s $end
$var wire 5 ) tmp [4:0] $end
$var wire 5 * sum2 [4:0] $end
$var wire 5 + sum [4:0] $end
$var wire 5 , d [4:0] $end
$scope module fb1 $end
$var wire 5 - a [4:0] $end
$var wire 5 . b [4:0] $end
$var wire 1 ! cout $end
$var wire 5 / s [4:0] $end
$var wire 5 0 c [4:0] $end
$scope module b1 $end
$var wire 1 1 a $end
$var wire 1 2 b $end
$var wire 1 3 carry $end
$var wire 1 4 sum $end
$upscope $end
$scope module b2 $end
$var wire 1 5 a $end
$var wire 1 6 b $end
$var wire 1 7 carryin $end
$var wire 1 8 carryout $end
$var wire 1 9 sum $end
$var wire 1 : w1 $end
$var wire 1 ; w2 $end
$var wire 1 < w3 $end
$upscope $end
$scope module b3 $end
$var wire 1 = a $end
$var wire 1 > b $end
$var wire 1 ? carryin $end
$var wire 1 @ carryout $end
$var wire 1 A sum $end
$var wire 1 B w1 $end
$var wire 1 C w2 $end
$var wire 1 D w3 $end
$upscope $end
$scope module b4 $end
$var wire 1 E a $end
$var wire 1 F b $end
$var wire 1 G carryin $end
$var wire 1 H carryout $end
$var wire 1 I sum $end
$var wire 1 J w1 $end
$var wire 1 K w2 $end
$var wire 1 L w3 $end
$upscope $end
$scope module b5 $end
$var wire 1 M a $end
$var wire 1 N b $end
$var wire 1 O carryin $end
$var wire 1 ! carryout $end
$var wire 1 P sum $end
$var wire 1 Q w1 $end
$var wire 1 R w2 $end
$var wire 1 S w3 $end
$upscope $end
$upscope $end
$scope module fb2 $end
$var wire 5 T a [4:0] $end
$var wire 5 U b [4:0] $end
$var wire 1 ! cout $end
$var wire 5 V s [4:0] $end
$var wire 5 W c [4:0] $end
$scope module b1 $end
$var wire 1 X a $end
$var wire 1 Y b $end
$var wire 1 Z carry $end
$var wire 1 [ sum $end
$upscope $end
$scope module b2 $end
$var wire 1 \ a $end
$var wire 1 ] b $end
$var wire 1 ^ carryin $end
$var wire 1 _ carryout $end
$var wire 1 ` sum $end
$var wire 1 a w1 $end
$var wire 1 b w2 $end
$var wire 1 c w3 $end
$upscope $end
$scope module b3 $end
$var wire 1 d a $end
$var wire 1 e b $end
$var wire 1 f carryin $end
$var wire 1 g carryout $end
$var wire 1 h sum $end
$var wire 1 i w1 $end
$var wire 1 j w2 $end
$var wire 1 k w3 $end
$upscope $end
$scope module b4 $end
$var wire 1 l a $end
$var wire 1 m b $end
$var wire 1 n carryin $end
$var wire 1 o carryout $end
$var wire 1 p sum $end
$var wire 1 q w1 $end
$var wire 1 r w2 $end
$var wire 1 s w3 $end
$upscope $end
$scope module b5 $end
$var wire 1 t a $end
$var wire 1 u b $end
$var wire 1 v carryin $end
$var wire 1 ! carryout $end
$var wire 1 w sum $end
$var wire 1 x w1 $end
$var wire 1 y w2 $end
$var wire 1 z w3 $end
$upscope $end
$upscope $end
$scope module s0 $end
$var wire 1 { a $end
$var wire 1 | out $end
$var wire 1 % s $end
$upscope $end
$scope module s1 $end
$var wire 1 } a $end
$var wire 1 ~ out $end
$var wire 1 % s $end
$upscope $end
$scope module s2 $end
$var wire 1 !" a $end
$var wire 1 "" out $end
$var wire 1 % s $end
$upscope $end
$scope module s3 $end
$var wire 1 #" a $end
$var wire 1 $" out $end
$var wire 1 % s $end
$upscope $end
$upscope $end
$upscope $end
$enddefinitions $end
#0
$dumpvars
x$"
x#"
x""
x!"
x~
x}
x|
x{
xz
xy
xx
xw
xv
xu
xt
xs
xr
xq
xp
xo
xn
xm
xl
xk
xj
xi
xh
xg
xf
xe
xd
xc
xb
xa
x`
x_
x^
x]
x\
x[
xZ
xY
xX
bxz W
bx V
bx U
bx T
xS
xR
xQ
xP
xO
xN
zM
xL
xK
xJ
xI
xH
xG
xF
xE
xD
xC
xB
xA
x@
x?
x>
x=
x<
x;
x:
x9
x8
x7
x6
x5
x4
x3
x2
x1
bxz 0
bx /
bx .
bzxxxx -
bx ,
bx +
bx *
bx )
bzxxxx (
bx '
bx &
x%
bx $
bx #
bx "
x!
$end
#10
0z
0v
0o
0s
0n
0g
0k
0f
0_
0c
0R
0K
0C
0;
0y
0^
0N
0F
0>
06
12
1|
1~
1""
1$"
0u
b0z W
0Z
0b
0j
0r
b1 )
b1 .
0{
0}
0!"
0#"
0Y
0]
0e
0m
0%
b0 $
b0 '
b0 ,
b0 U
b0 #
b0 &
#20
0|
1{
b1 $
b1 '
#30
1|
0~
0{
1}
b10 $
b10 '
#40
0|
1{
b11 $
b11 '
#50
1|
1~
0""
0{
0}
1!"
b100 $
b100 '
#60
0|
1{
b101 $
b101 '
#70
1|
0~
0{
1}
b110 $
b110 '
#80
0|
1{
b111 $
b111 '
#90
1|
1~
1""
0$"
0{
0}
0!"
1#"
b1000 $
b1000 '
#100
0|
1{
b1001 $
b1001 '
#110
1|
0~
0{
1}
b1010 $
b1010 '
#120
0|
1{
b1011 $
b1011 '
#130
1|
1~
0""
0{
0}
1!"
b1100 $
b1100 '
#140
0|
1{
b1101 $
b1101 '
#150
1|
0~
0{
1}
b1110 $
b1110 '
#160
0|
1{
b1111 $
b1111 '
#170
xz
xv
xo
xs
xn
xg
xk
xf
x_
xc
1|
1~
1""
1$"
x^
bxz W
xZ
0{
0}
0!"
0#"
1Y
b0 $
b0 '
b1 ,
b1 U
b1 #
b1 &
#180
0|
1{
b1 $
b1 '
#190
1|
0~
0{
1}
b10 $
b10 '
#200
0|
1{
b11 $
b11 '
#210
1|
1~
0""
0{
0}
1!"
b100 $
b100 '
#220
0|
1{
b101 $
b101 '
#230
1|
0~
0{
1}
b110 $
b110 '
#240
0|
1{
b111 $
b111 '
#250
1|
1~
1""
0$"
0{
0}
0!"
1#"
b1000 $
b1000 '
#260
0|
1{
b1001 $
b1001 '
#270
1|
0~
0{
1}
b1010 $
b1010 '
#280
0|
1{
b1011 $
b1011 '
#290
1|
1~
0""
0{
0}
1!"
b1100 $
b1100 '
#300
0|
1{
b1101 $
b1101 '
#310
1|
0~
0{
1}
b1110 $
b1110 '
#320
0|
1{
b1111 $
b1111 '
#330
0c
1|
1~
1""
1$"
0^
bx0z W
0Z
xb
0{
0}
0!"
0#"
0Y
1]
b0 $
b0 '
b10 ,
b10 U
b10 #
b10 &
#340
0|
1{
b1 $
b1 '
#350
1|
0~
0{
1}
b10 $
b10 '
#360
0|
1{
b11 $
b11 '
#370
1|
1~
0""
0{
0}
1!"
b100 $
b100 '
#380
0|
1{
b101 $
b101 '
#390
1|
0~
0{
1}
b110 $
b110 '
#400
0|
1{
b111 $
b111 '
#410
1|
1~
1""
0$"
0{
0}
0!"
1#"
b1000 $
b1000 '
#420
0|
1{
b1001 $
b1001 '
#430
1|
0~
0{
1}
b1010 $
b1010 '
#440
0|
1{
b1011 $
b1011 '
#450
1|
1~
0""
0{
0}
1!"
b1100 $
b1100 '
#460
0|
1{
b1101 $
b1101 '
#470
1|
0~
0{
1}
b1110 $
b1110 '
#480
0|
1{
b1111 $
b1111 '
#490
xc
1|
1~
1""
1$"
x^
bxz W
xZ
0{
0}
0!"
0#"
1Y
b0 $
b0 '
b11 ,
b11 U
b11 #
b11 &
#500
0|
1{
b1 $
b1 '
#510
1|
0~
0{
1}
b10 $
b10 '
#520
0|
1{
b11 $
b11 '
#530
1|
1~
0""
0{
0}
1!"
b100 $
b100 '
#540
0|
1{
b101 $
b101 '
#550
1|
0~
0{
1}
b110 $
b110 '
#560
0|
1{
b111 $
b111 '
#570
1|
1~
1""
0$"
0{
0}
0!"
1#"
b1000 $
b1000 '
#580
0|
1{
b1001 $
b1001 '
#590
1|
0~
0{
1}
b1010 $
b1010 '
#600
0|
1{
b1011 $
b1011 '
#610
1|
1~
0""
0{
0}
1!"
b1100 $
b1100 '
#620
0|
1{
b1101 $
b1101 '
#630
1|
0~
0{
1}
b1110 $
b1110 '
#640
0|
1{
b1111 $
b1111 '
#650
0k
0f
0_
0c
1|
1~
1""
1$"
0^
bx00z W
0Z
0b
xj
0{
0}
0!"
0#"
0Y
0]
1e
b0 $
b0 '
b100 ,
b100 U
b100 #
b100 &
#660
0|
1{
b1 $
b1 '
#670
1|
0~
0{
1}
b10 $
b10 '
#680
0|
1{
b11 $
b11 '
#690
1|
1~
0""
0{
0}
1!"
b100 $
b100 '
#700
0|
1{
b101 $
b101 '
#710
1|
0~
0{
1}
b110 $
b110 '
#720
0|
1{
b111 $
b111 '
#730
1|
1~
1""
0$"
0{
0}
0!"
1#"
b1000 $
b1000 '
#740
0|
1{
b1001 $
b1001 '
#750
1|
0~
0{
1}
b1010 $
b1010 '
#760
0|
1{
b1011 $
b1011 '
#770
1|
1~
0""
0{
0}
1!"
b1100 $
b1100 '
#780
0|
1{
b1101 $
b1101 '
#790
1|
0~
0{
1}
b1110 $
b1110 '
#800
0|
1{
b1111 $
b1111 '
#810
xk
xf
x_
xc
1|
1~
1""
1$"
x^
bxz W
xZ
0{
0}
0!"
0#"
1Y
b0 $
b0 '
b101 ,
b101 U
b101 #
b101 &
#820
0|
1{
b1 $
b1 '
#830
1|
0~
0{
1}
b10 $
b10 '
#840
0|
1{
b11 $
b11 '
#850
1|
1~
0""
0{
0}
1!"
b100 $
b100 '
#860
0|
1{
b101 $
b101 '
#870
1|
0~
0{
1}
b110 $
b110 '
#880
0|
1{
b111 $
b111 '
#890
1|
1~
1""
0$"
0{
0}
0!"
1#"
b1000 $
b1000 '
#900
0|
1{
b1001 $
b1001 '
#910
1|
0~
0{
1}
b1010 $
b1010 '
#920
0|
1{
b1011 $
b1011 '
#930
1|
1~
0""
0{
0}
1!"
b1100 $
b1100 '
#940
0|
1{
b1101 $
b1101 '
#950
1|
0~
0{
1}
b1110 $
b1110 '
#960
0|
1{
b1111 $
b1111 '
#970
0c
1|
1~
1""
1$"
0^
bx0z W
0Z
xb
0{
0}
0!"
0#"
0Y
1]
b0 $
b0 '
b110 ,
b110 U
b110 #
b110 &
#980
0|
1{
b1 $
b1 '
#990
1|
0~
0{
1}
b10 $
b10 '
#1000
0|
1{
b11 $
b11 '
#1010
1|
1~
0""
0{
0}
1!"
b100 $
b100 '
#1020
0|
1{
b101 $
b101 '
#1030
1|
0~
0{
1}
b110 $
b110 '
#1040
0|
1{
b111 $
b111 '
#1050
1|
1~
1""
0$"
0{
0}
0!"
1#"
b1000 $
b1000 '
#1060
0|
1{
b1001 $
b1001 '
#1070
1|
0~
0{
1}
b1010 $
b1010 '
#1080
0|
1{
b1011 $
b1011 '
#1090
1|
1~
0""
0{
0}
1!"
b1100 $
b1100 '
#1100
0|
1{
b1101 $
b1101 '
#1110
1|
0~
0{
1}
b1110 $
b1110 '
#1120
0|
1{
b1111 $
b1111 '
#1130
xc
1|
1~
1""
1$"
x^
bxz W
xZ
0{
0}
0!"
0#"
1Y
b0 $
b0 '
b111 ,
b111 U
b111 #
b111 &
#1140
0|
1{
b1 $
b1 '
#1150
1|
0~
0{
1}
b10 $
b10 '
#1160
0|
1{
b11 $
b11 '
#1170
1|
1~
0""
0{
0}
1!"
b100 $
b100 '
#1180
0|
1{
b101 $
b101 '
#1190
1|
0~
0{
1}
b110 $
b110 '
#1200
0|
1{
b111 $
b111 '
#1210
1|
1~
1""
0$"
0{
0}
0!"
1#"
b1000 $
b1000 '
#1220
0|
1{
b1001 $
b1001 '
#1230
1|
0~
0{
1}
b1010 $
b1010 '
#1240
0|
1{
b1011 $
b1011 '
#1250
1|
1~
0""
0{
0}
1!"
b1100 $
b1100 '
#1260
0|
1{
b1101 $
b1101 '
#1270
1|
0~
0{
1}
b1110 $
b1110 '
#1280
0|
1{
b1111 $
b1111 '
#1290
0s
0n
0g
0k
0f
0_
0c
1|
1~
1""
1$"
xy
0^
1u
bx000z W
0Z
0b
0j
xr
0{
0}
0!"
0#"
0Y
0]
0e
1m
b0 $
b0 '
b11000 ,
b11000 U
b1000 #
b1000 &
#1300
0|
1{
b1 $
b1 '
#1310
1|
0~
0{
1}
b10 $
b10 '
#1320
0|
1{
b11 $
b11 '
#1330
1|
1~
0""
0{
0}
1!"
b100 $
b100 '
#1340
0|
1{
b101 $
b101 '
#1350
1|
0~
0{
1}
b110 $
b110 '
#1360
0|
1{
b111 $
b111 '
#1370
1|
1~
1""
0$"
0{
0}
0!"
1#"
b1000 $
b1000 '
#1380
0|
1{
b1001 $
b1001 '
#1390
1|
0~
0{
1}
b1010 $
b1010 '
#1400
0|
1{
b1011 $
b1011 '
#1410
1|
1~
0""
0{
0}
1!"
b1100 $
b1100 '
#1420
0|
1{
b1101 $
b1101 '
#1430
1|
0~
0{
1}
b1110 $
b1110 '
#1440
0|
1{
b1111 $
b1111 '
#1450
xs
xn
xg
xk
xf
x_
xc
1|
1~
1""
1$"
x^
bxz W
xZ
0{
0}
0!"
0#"
1Y
b0 $
b0 '
b11001 ,
b11001 U
b1001 #
b1001 &
#1460
0|
1{
b1 $
b1 '
#1470
1|
0~
0{
1}
b10 $
b10 '
#1480
0|
1{
b11 $
b11 '
#1490
1|
1~
0""
0{
0}
1!"
b100 $
b100 '
#1500
0|
1{
b101 $
b101 '
#1510
1|
0~
0{
1}
b110 $
b110 '
#1520
0|
1{
b111 $
b111 '
#1530
1|
1~
1""
0$"
0{
0}
0!"
1#"
b1000 $
b1000 '
#1540
0|
1{
b1001 $
b1001 '
#1550
1|
0~
0{
1}
b1010 $
b1010 '
#1560
0|
1{
b1011 $
b1011 '
#1570
1|
1~
0""
0{
0}
1!"
b1100 $
b1100 '
#1580
0|
1{
b1101 $
b1101 '
#1590
1|
0~
0{
1}
b1110 $
b1110 '
#1600
0|
1{
b1111 $
b1111 '
#1610
0c
1|
1~
1""
1$"
0^
bx0z W
0Z
xb
0{
0}
0!"
0#"
0Y
1]
b0 $
b0 '
b11010 ,
b11010 U
b1010 #
b1010 &
#1620
0|
1{
b1 $
b1 '
#1630
1|
0~
0{
1}
b10 $
b10 '
#1640
0|
1{
b11 $
b11 '
#1650
1|
1~
0""
0{
0}
1!"
b100 $
b100 '
#1660
0|
1{
b101 $
b101 '
#1670
1|
0~
0{
1}
b110 $
b110 '
#1680
0|
1{
b111 $
b111 '
#1690
1|
1~
1""
0$"
0{
0}
0!"
1#"
b1000 $
b1000 '
#1700
0|
1{
b1001 $
b1001 '
#1710
1|
0~
0{
1}
b1010 $
b1010 '
#1720
0|
1{
b1011 $
b1011 '
#1730
1|
1~
0""
0{
0}
1!"
b1100 $
b1100 '
#1740
0|
1{
b1101 $
b1101 '
#1750
1|
0~
0{
1}
b1110 $
b1110 '
#1760
0|
1{
b1111 $
b1111 '
#1770
xc
1|
1~
1""
1$"
x^
bxz W
xZ
0{
0}
0!"
0#"
1Y
b0 $
b0 '
b11011 ,
b11011 U
b1011 #
b1011 &
#1780
0|
1{
b1 $
b1 '
#1790
1|
0~
0{
1}
b10 $
b10 '
#1800
0|
1{
b11 $
b11 '
#1810
1|
1~
0""
0{
0}
1!"
b100 $
b100 '
#1820
0|
1{
b101 $
b101 '
#1830
1|
0~
0{
1}
b110 $
b110 '
#1840
0|
1{
b111 $
b111 '
#1850
1|
1~
1""
0$"
0{
0}
0!"
1#"
b1000 $
b1000 '
#1860
0|
1{
b1001 $
b1001 '
#1870
1|
0~
0{
1}
b1010 $
b1010 '
#1880
0|
1{
b1011 $
b1011 '
#1890
1|
1~
0""
0{
0}
1!"
b1100 $
b1100 '
#1900
0|
1{
b1101 $
b1101 '
#1910
1|
0~
0{
1}
b1110 $
b1110 '
#1920
0|
1{
b1111 $
b1111 '
#1930
0k
0f
0_
0c
1|
1~
1""
1$"
0^
bx00z W
0Z
0b
xj
0{
0}
0!"
0#"
0Y
0]
1e
b0 $
b0 '
b11100 ,
b11100 U
b1100 #
b1100 &
#1940
0|
1{
b1 $
b1 '
#1950
1|
0~
0{
1}
b10 $
b10 '
#1960
0|
1{
b11 $
b11 '
#1970
1|
1~
0""
0{
0}
1!"
b100 $
b100 '
#1980
0|
1{
b101 $
b101 '
#1990
1|
0~
0{
1}
b110 $
b110 '
#2000
0|
1{
b111 $
b111 '
#2010
1|
1~
1""
0$"
0{
0}
0!"
1#"
b1000 $
b1000 '
#2020
0|
1{
b1001 $
b1001 '
#2030
1|
0~
0{
1}
b1010 $
b1010 '
#2040
0|
1{
b1011 $
b1011 '
#2050
1|
1~
0""
0{
0}
1!"
b1100 $
b1100 '
#2060
0|
1{
b1101 $
b1101 '
#2070
1|
0~
0{
1}
b1110 $
b1110 '
#2080
0|
1{
b1111 $
b1111 '
#2090
xk
xf
x_
xc
1|
1~
1""
1$"
x^
bxz W
xZ
0{
0}
0!"
0#"
1Y
b0 $
b0 '
b11101 ,
b11101 U
b1101 #
b1101 &
#2100
0|
1{
b1 $
b1 '
#2110
1|
0~
0{
1}
b10 $
b10 '
#2120
0|
1{
b11 $
b11 '
#2130
1|
1~
0""
0{
0}
1!"
b100 $
b100 '
#2140
0|
1{
b101 $
b101 '
#2150
1|
0~
0{
1}
b110 $
b110 '
#2160
0|
1{
b111 $
b111 '
#2170
1|
1~
1""
0$"
0{
0}
0!"
1#"
b1000 $
b1000 '
#2180
0|
1{
b1001 $
b1001 '
#2190
1|
0~
0{
1}
b1010 $
b1010 '
#2200
0|
1{
b1011 $
b1011 '
#2210
1|
1~
0""
0{
0}
1!"
b1100 $
b1100 '
#2220
0|
1{
b1101 $
b1101 '
#2230
1|
0~
0{
1}
b1110 $
b1110 '
#2240
0|
1{
b1111 $
b1111 '
#2250
0c
1|
1~
1""
1$"
0^
bx0z W
0Z
xb
0{
0}
0!"
0#"
0Y
1]
b0 $
b0 '
b11110 ,
b11110 U
b1110 #
b1110 &
#2260
0|
1{
b1 $
b1 '
#2270
1|
0~
0{
1}
b10 $
b10 '
#2280
0|
1{
b11 $
b11 '
#2290
1|
1~
0""
0{
0}
1!"
b100 $
b100 '
#2300
0|
1{
b101 $
b101 '
#2310
1|
0~
0{
1}
b110 $
b110 '
#2320
0|
1{
b111 $
b111 '
#2330
1|
1~
1""
0$"
0{
0}
0!"
1#"
b1000 $
b1000 '
#2340
0|
1{
b1001 $
b1001 '
#2350
1|
0~
0{
1}
b1010 $
b1010 '
#2360
0|
1{
b1011 $
b1011 '
#2370
1|
1~
0""
0{
0}
1!"
b1100 $
b1100 '
#2380
0|
1{
b1101 $
b1101 '
#2390
1|
0~
0{
1}
b1110 $
b1110 '
#2400
0|
1{
b1111 $
b1111 '
#2410
xc
1|
1~
1""
1$"
x^
bxz W
xZ
0{
0}
0!"
0#"
1Y
b0 $
b0 '
b11111 ,
b11111 U
b1111 #
b1111 &
#2420
0|
1{
b1 $
b1 '
#2430
1|
0~
0{
1}
b10 $
b10 '
#2440
0|
1{
b11 $
b11 '
#2450
1|
1~
0""
0{
0}
1!"
b100 $
b100 '
#2460
0|
1{
b101 $
b101 '
#2470
1|
0~
0{
1}
b110 $
b110 '
#2480
0|
1{
b111 $
b111 '
#2490
1|
1~
1""
0$"
0{
0}
0!"
1#"
b1000 $
b1000 '
#2500
0|
1{
b1001 $
b1001 '
#2510
1|
0~
0{
1}
b1010 $
b1010 '
#2520
0|
1{
b1011 $
b1011 '
#2530
1|
1~
0""
0{
0}
1!"
b1100 $
b1100 '
#2540
0|
1{
b1101 $
b1101 '
#2550
1|
0~
0{
1}
b1110 $
b1110 '
#2560
0|
1{
b1111 $
b1111 '
#2570
0!
0S
0z
0O
0v
0H
0o
0L
0s
0G
0n
0@
0g
0D
0k
0?
0f
08
0<
0_
07
0c
0R
0K
0C
0;
b0z 0
03
0y
0^
0N
0F
0>
06
02
0u
b0z W
0Z
0b
0j
0r
b0 )
b0 .
0{
0}
0!"
0#"
0Y
0]
0e
0m
1%
b0 $
b0 '
b0 ,
b0 U
b0 #
b0 &
#2580
1|
1{
b1 $
b1 '
#2590
0|
1~
0{
1}
b10 $
b10 '
#2600
1|
1{
b11 $
b11 '
#2610
0|
0~
1""
0{
0}
1!"
b100 $
b100 '
#2620
1|
1{
b101 $
b101 '
#2630
0|
1~
0{
1}
b110 $
b110 '
#2640
1|
1{
b111 $
b111 '
#2650
0|
0~
0""
1$"
0{
0}
0!"
1#"
b1000 $
b1000 '
#2660
1|
1{
b1001 $
b1001 '
#2670
0|
1~
0{
1}
b1010 $
b1010 '
#2680
1|
1{
b1011 $
b1011 '
#2690
0|
0~
1""
0{
0}
1!"
b1100 $
b1100 '
#2700
1|
1{
b1101 $
b1101 '
#2710
0|
1~
0{
1}
b1110 $
b1110 '
#2720
1|
1{
b1111 $
b1111 '
#2730
x!
xz
xv
xo
xs
xn
xg
xk
xf
x_
xc
0|
0~
0""
0$"
x^
bxz W
xZ
0{
0}
0!"
0#"
1Y
b0 $
b0 '
b1 ,
b1 U
b1 #
b1 &
#2740
1|
1{
b1 $
b1 '
#2750
0|
1~
0{
1}
b10 $
b10 '
#2760
1|
1{
b11 $
b11 '
#2770
0|
0~
1""
0{
0}
1!"
b100 $
b100 '
#2780
1|
1{
b101 $
b101 '
#2790
0|
1~
0{
1}
b110 $
b110 '
#2800
1|
1{
b111 $
b111 '
#2810
0|
0~
0""
1$"
0{
0}
0!"
1#"
b1000 $
b1000 '
#2820
1|
1{
b1001 $
b1001 '
#2830
0|
1~
0{
1}
b1010 $
b1010 '
#2840
1|
1{
b1011 $
b1011 '
#2850
0|
0~
1""
0{
0}
1!"
b1100 $
b1100 '
#2860
1|
1{
b1101 $
b1101 '
#2870
0|
1~
0{
1}
b1110 $
b1110 '
#2880
1|
1{
b1111 $
b1111 '
#2890
0c
0|
0~
0""
0$"
0^
bx0z W
0Z
xb
0{
0}
0!"
0#"
0Y
1]
b0 $
b0 '
b10 ,
b10 U
b10 #
b10 &
#2900
1|
1{
b1 $
b1 '
#2910
0|
1~
0{
1}
b10 $
b10 '
#2920
1|
1{
b11 $
b11 '
#2930
0|
0~
1""
0{
0}
1!"
b100 $
b100 '
#2940
1|
1{
b101 $
b101 '
#2950
0|
1~
0{
1}
b110 $
b110 '
#2960
1|
1{
b111 $
b111 '
#2970
0|
0~
0""
1$"
0{
0}
0!"
1#"
b1000 $
b1000 '
#2980
1|
1{
b1001 $
b1001 '
#2990
0|
1~
0{
1}
b1010 $
b1010 '
#3000
1|
1{
b1011 $
b1011 '
#3010
0|
0~
1""
0{
0}
1!"
b1100 $
b1100 '
#3020
1|
1{
b1101 $
b1101 '
#3030
0|
1~
0{
1}
b1110 $
b1110 '
#3040
1|
1{
b1111 $
b1111 '
#3050
xc
0|
0~
0""
0$"
x^
bxz W
xZ
0{
0}
0!"
0#"
1Y
b0 $
b0 '
b11 ,
b11 U
b11 #
b11 &
#3060
1|
1{
b1 $
b1 '
#3070
0|
1~
0{
1}
b10 $
b10 '
#3080
1|
1{
b11 $
b11 '
#3090
0|
0~
1""
0{
0}
1!"
b100 $
b100 '
#3100
1|
1{
b101 $
b101 '
#3110
0|
1~
0{
1}
b110 $
b110 '
#3120
1|
1{
b111 $
b111 '
#3130
0|
0~
0""
1$"
0{
0}
0!"
1#"
b1000 $
b1000 '
#3140
1|
1{
b1001 $
b1001 '
#3150
0|
1~
0{
1}
b1010 $
b1010 '
#3160
1|
1{
b1011 $
b1011 '
#3170
0|
0~
1""
0{
0}
1!"
b1100 $
b1100 '
#3180
1|
1{
b1101 $
b1101 '
#3190
0|
1~
0{
1}
b1110 $
b1110 '
#3200
1|
1{
b1111 $
b1111 '
#3210
0k
0f
0_
0c
0|
0~
0""
0$"
0^
bx00z W
0Z
0b
xj
0{
0}
0!"
0#"
0Y
0]
1e
b0 $
b0 '
b100 ,
b100 U
b100 #
b100 &
#3220
1|
1{
b1 $
b1 '
#3230
0|
1~
0{
1}
b10 $
b10 '
#3240
1|
1{
b11 $
b11 '
#3250
0|
0~
1""
0{
0}
1!"
b100 $
b100 '
#3260
1|
1{
b101 $
b101 '
#3270
0|
1~
0{
1}
b110 $
b110 '
#3280
1|
1{
b111 $
b111 '
#3290
0|
0~
0""
1$"
0{
0}
0!"
1#"
b1000 $
b1000 '
#3300
1|
1{
b1001 $
b1001 '
#3310
0|
1~
0{
1}
b1010 $
b1010 '
#3320
1|
1{
b1011 $
b1011 '
#3330
0|
0~
1""
0{
0}
1!"
b1100 $
b1100 '
#3340
1|
1{
b1101 $
b1101 '
#3350
0|
1~
0{
1}
b1110 $
b1110 '
#3360
1|
1{
b1111 $
b1111 '
#3370
xk
xf
x_
xc
0|
0~
0""
0$"
x^
bxz W
xZ
0{
0}
0!"
0#"
1Y
b0 $
b0 '
b101 ,
b101 U
b101 #
b101 &
#3380
1|
1{
b1 $
b1 '
#3390
0|
1~
0{
1}
b10 $
b10 '
#3400
1|
1{
b11 $
b11 '
#3410
0|
0~
1""
0{
0}
1!"
b100 $
b100 '
#3420
1|
1{
b101 $
b101 '
#3430
0|
1~
0{
1}
b110 $
b110 '
#3440
1|
1{
b111 $
b111 '
#3450
0|
0~
0""
1$"
0{
0}
0!"
1#"
b1000 $
b1000 '
#3460
1|
1{
b1001 $
b1001 '
#3470
0|
1~
0{
1}
b1010 $
b1010 '
#3480
1|
1{
b1011 $
b1011 '
#3490
0|
0~
1""
0{
0}
1!"
b1100 $
b1100 '
#3500
1|
1{
b1101 $
b1101 '
#3510
0|
1~
0{
1}
b1110 $
b1110 '
#3520
1|
1{
b1111 $
b1111 '
#3530
0c
0|
0~
0""
0$"
0^
bx0z W
0Z
xb
0{
0}
0!"
0#"
0Y
1]
b0 $
b0 '
b110 ,
b110 U
b110 #
b110 &
#3540
1|
1{
b1 $
b1 '
#3550
0|
1~
0{
1}
b10 $
b10 '
#3560
1|
1{
b11 $
b11 '
#3570
0|
0~
1""
0{
0}
1!"
b100 $
b100 '
#3580
1|
1{
b101 $
b101 '
#3590
0|
1~
0{
1}
b110 $
b110 '
#3600
1|
1{
b111 $
b111 '
#3610
0|
0~
0""
1$"
0{
0}
0!"
1#"
b1000 $
b1000 '
#3620
1|
1{
b1001 $
b1001 '
#3630
0|
1~
0{
1}
b1010 $
b1010 '
#3640
1|
1{
b1011 $
b1011 '
#3650
0|
0~
1""
0{
0}
1!"
b1100 $
b1100 '
#3660
1|
1{
b1101 $
b1101 '
#3670
0|
1~
0{
1}
b1110 $
b1110 '
#3680
1|
1{
b1111 $
b1111 '
#3690
xc
0|
0~
0""
0$"
x^
bxz W
xZ
0{
0}
0!"
0#"
1Y
b0 $
b0 '
b111 ,
b111 U
b111 #
b111 &
#3700
1|
1{
b1 $
b1 '
#3710
0|
1~
0{
1}
b10 $
b10 '
#3720
1|
1{
b11 $
b11 '
#3730
0|
0~
1""
0{
0}
1!"
b100 $
b100 '
#3740
1|
1{
b101 $
b101 '
