Exp10/T3/modules.v
module five_bit(a,b,s,cout);

input [4:0] a,b;
output [4:0] s,c;
output cout;

ha b1(a[0],b[0],s[0],c[1]);
fa b2(a[1],b[1],c[1],s[1],c[2]);
fa b3(a[2],b[2],c[2],s[2],c[3]);
fa b4(a[3],b[3],c[3],s[3],c[4]);
fa b5(a[4],b[4],c[4],s[4],cout);

endmodule

module comp(s,a,out);

input s,a;
output out;

assign out = ~(s ^ a);


endmodule

module ha(a , b, sum , carry);

input a,b;
output sum,carry;

xor x1 (sum , a ,b ) ;
and a1 ( carry , a , b ) ;

endmodule

module fa(a , b , carryin , sum , carryout);

input a,b,carryin;
output sum,carryout;
wire w1,w2,w3;

xor x1 ( w1 , a ,b ) ;
and a1 ( w2 , a , b ) ;
xor x2 ( sum , carryin , w1 );
and a2 ( w3 , w1 , carryin );
or  o3 ( carryout , w2 ,w3 );

endmodule

Exp10/T3/exp.v
module t3(a,b,s,sum2,cout);

input [4:0] a;
input [3:0] b;
input s;
wire [4:0] tmp;
wire [4:0] c,sum;
output cout;
output [4:0] sum2;

comp s0(s,b[0],c[0]);
comp s1(s,b[1],c[1]);
comp s2(s,b[2],c[2]);
comp s3(s,b[3],c[3]);
assign c[4] = c[3];
assign a[4] = a[3];

assign tmp[0]=~s;
assign tmp[1]=0;
assign tmp[2]=0;
assign tmp[3]=0;
assign tmp[4]=0;



five_bit fb1(c,tmp,sum,cout);
assign sum[4] = cout;
five_bit fb2(sum,a,sum2,cout);


endmodule

Exp10/T3/test02.v
module test_four_bit_adder;                 //test bench module                            //outputs from full adder
reg [3:0] a,b;
reg s;
wire [4:0]sum2;
wire cout;                    //inputs to the full adder adder module
t3 DUT(a,b,s,sum2,cout);           //instantiate the device under test (5 bit adder)
initial
begin
$dumpfile("testfive.vcd");
$dumpvars(0,test_four_bit_adder);
$monitor("At time = %t,a = %b,b = %b,s = %b,output= %b",$time,a,b,s,sum2);
#10 a = 4'b0000; b = 4'b0000; s = 1'b0;
#10 a = 4'b0000; b = 4'b0001; s = 1'b0;
#10 a = 4'b0000; b = 4'b0010; s = 1'b0;
#10 a = 4'b1111; b = 4'b0111; s = 1'b1;
#10 a = 4'b1111; b = 4'b1000; s = 1'b1;
#10 a = 4'b1111; b = 4'b1001; s = 1'b1;
#10 a = 4'b1111; b = 4'b1010; s = 1'b1;
#10 a = 4'b1111; b = 4'b1011; s = 1'b1;
#10 a = 4'b1111; b = 4'b1100; s = 1'b1;
#10 a = 4'b1111; b = 4'b1101; s = 1'b1;
#10 a = 4'b1111; b = 4'b1110; s = 1'b1;
#10 a = 4'b1111; b = 4'b1111; s = 1'b1;

#10 $finish;
end
endmodule

Exp10/T3/testfive.vcd
$date
	Tue Jan 29 15:28:41 2019
$end
$version
	Icarus Verilog
$end
$timescale
	1s
$end
$scope module test_four_bit_adder $end
$var wire 1 ! cout $end
$var wire 5 " sum2 [4:0] $end
$var reg 4 # a [3:0] $end
$var reg 4 $ b [3:0] $end
$var reg 1 % s $end
$scope module DUT $end
$var wire 5 & a [4:0] $end
$var wire 4 ' b [3:0] $end
$var wire 1 ! cout $end
$var wire 1 % s $end
$var wire 5 ( sum [4:0] $end
$var wire 5 ) tmp [4:0] $end
$var wire 5 * sum2 [4:0] $end
$var wire 5 + c [4:0] $end
$scope module fb1 $end
$var wire 5 , a [4:0] $end
$var wire 5 - b [4:0] $end
$var wire 1 ! cout $end
$var wire 5 . s [4:0] $end
$var wire 5 / c [4:0] $end
$scope module b1 $end
$var wire 1 0 a $end
$var wire 1 1 b $end
$var wire 1 2 carry $end
$var wire 1 3 sum $end
$upscope $end
$scope module b2 $end
$var wire 1 4 a $end
$var wire 1 5 b $end
$var wire 1 6 carryin $end
$var wire 1 7 carryout $end
$var wire 1 8 sum $end
$var wire 1 9 w1 $end
$var wire 1 : w2 $end
$var wire 1 ; w3 $end
$upscope $end
$scope module b3 $end
$var wire 1 < a $end
$var wire 1 = b $end
$var wire 1 > carryin $end
$var wire 1 ? carryout $end
$var wire 1 @ sum $end
$var wire 1 A w1 $end
$var wire 1 B w2 $end
$var wire 1 C w3 $end
$upscope $end
$scope module b4 $end
$var wire 1 D a $end
$var wire 1 E b $end
$var wire 1 F carryin $end
$var wire 1 G carryout $end
$var wire 1 H sum $end
$var wire 1 I w1 $end
$var wire 1 J w2 $end
$var wire 1 K w3 $end
$upscope $end
$scope module b5 $end
$var wire 1 L a $end
$var wire 1 M b $end
$var wire 1 N carryin $end
$var wire 1 ! carryout $end
$var wire 1 O sum $end
$var wire 1 P w1 $end
$var wire 1 Q w2 $end
$var wire 1 R w3 $end
$upscope $end
$upscope $end
$scope module fb2 $end
$var wire 5 S a [4:0] $end
$var wire 5 T b [4:0] $end
$var wire 1 ! cout $end
$var wire 5 U s [4:0] $end
$var wire 5 V c [4:0] $end
$scope module b1 $end
$var wire 1 W a $end
$var wire 1 X b $end
$var wire 1 Y carry $end
$var wire 1 Z sum $end
$upscope $end
$scope module b2 $end
$var wire 1 [ a $end
$var wire 1 \ b $end
$var wire 1 ] carryin $end
$var wire 1 ^ carryout $end
$var wire 1 _ sum $end
$var wire 1 ` w1 $end
$var wire 1 a w2 $end
$var wire 1 b w3 $end
$upscope $end
$scope module b3 $end
$var wire 1 c a $end
$var wire 1 d b $end
$var wire 1 e carryin $end
$var wire 1 f carryout $end
$var wire 1 g sum $end
$var wire 1 h w1 $end
$var wire 1 i w2 $end
$var wire 1 j w3 $end
$upscope $end
$scope module b4 $end
$var wire 1 k a $end
$var wire 1 l b $end
$var wire 1 m carryin $end
$var wire 1 n carryout $end
$var wire 1 o sum $end
$var wire 1 p w1 $end
$var wire 1 q w2 $end
$var wire 1 r w3 $end
$upscope $end
$scope module b5 $end
$var wire 1 s a $end
$var wire 1 t b $end
$var wire 1 u carryin $end
$var wire 1 ! carryout $end
$var wire 1 v sum $end
$var wire 1 w w1 $end
$var wire 1 x w2 $end
$var wire 1 y w3 $end
$upscope $end
$upscope $end
$scope module s0 $end
$var wire 1 z a $end
$var wire 1 { out $end
$var wire 1 % s $end
$upscope $end
$scope module s1 $end
$var wire 1 | a $end
$var wire 1 } out $end
$var wire 1 % s $end
$upscope $end
$scope module s2 $end
$var wire 1 ~ a $end
$var wire 1 !" out $end
$var wire 1 % s $end
$upscope $end
$scope module s3 $end
$var wire 1 "" a $end
$var wire 1 #" out $end
$var wire 1 % s $end
$upscope $end
$upscope $end
$upscope $end
$enddefinitions $end
#0
$dumpvars
x#"
x""
x!"
x~
x}
x|
x{
xz
xy
xx
xw
xv
xu
xt
xs
xr
xq
xp
xo
xn
xm
xl
xk
xj
xi
xh
xg
xf
xe
xd
xc
xb
xa
x`
x_
x^
x]
x\
x[
xZ
xY
xX
xW
bxz V
bx U
bx T
bx S
xR
0Q
xP
xO
xN
0M
xL
xK
0J
xI
xH
xG
xF
0E
xD
xC
0B
xA
x@
x?
x>
0=
x<
x;
0:
x9
x8
x7
x6
05
x4
x3
x2
x1
x0
bxz /
bx .
b0x -
bx ,
bx +
bx *
b0x )
bx (
bx '
bx &
x%
bx $
bx #
bx "
x!
$end
#10
0o
0O
1R
0p
1N
0y
0k
1G
0u
0g
0H
1K
0n
0h
1F
0r
0c
1?
0m
0_
0@
1C
0f
0`
1>
0j
0[
17
0e
bx0000 "
bx0000 *
bx0000 U
0Z
08
1;
1P
0^
0W
16
19
1A
1L
1I
0b
bx0000 (
bx0000 .
bx0000 S
03
b1111z /
12
10
14
1<
1D
0x
0]
11
1{
1}
1!"
b11111 +
b11111 ,
1#"
0t
b0z V
0Y
0a
0i
0q
b1 )
b1 -
0z
0|
0~
0""
0X
0\
0d
0l
0%
b0 $
b0 '
b0 &
b0 T
b0 #
#20
0!
1o
1O
0R
1p
0N
1k
0G
1g
1H
0K
1h
0F
1c
0?
1_
1@
0C
1`
0>
1[
07
bx1111 "
bx1111 *
bx1111 U
1Z
18
0;
1W
06
bx1111 (
bx1111 .
bx1111 S
13
b0z /
02
00
b11110 +
b11110 ,
0{
1z
b1 $
b1 '
#30
1_
1`
bx1110 "
bx1110 *
bx1110 U
0Z
1[
0W
16
18
bx1110 (
bx1110 .
bx1110 S
03
b1z /
12
09
10
04
1{
b11101 +
b11101 ,
0}
0z
1|
b10 $
b10 '
#40
0_
0`
0[
bx1101 "
bx1101 *
bx1101 U
1Z
08
1W
06
bx1101 (
bx1101 .
bx1101 S
13
b0z /
02
00
b11100 +
b11100 ,
0{
1z
b11 $
b11 '
#50
1>
0_
1g
17
0`
1h
bx1100 "
bx1100 *
bx1100 U
0Z
1;
0[
1c
0W
16
08
1@
bx1100 (
bx1100 .
bx1100 S
03
b11z /
12
19
0A
10
14
0<
1{
1}
b11011 +
b11011 ,
0!"
0z
0|
1~
b100 $
b100 '
#60
0g
0h
0c
1_
0@
1`
0>
1[
07
bx1011 "
bx1011 *
bx1011 U
1Z
18
0;
1W
06
bx1011 (
bx1011 .
bx1011 S
13
b0z /
02
00
b11010 +
b11010 ,
0{
1z
b101 $
b101 '
#70
1_
1`
bx1010 "
bx1010 *
bx1010 U
0Z
1[
0W
16
18
bx1010 (
bx1010 .
bx1010 S
03
b1z /
12
09
10
04
1{
b11001 +
b11001 ,
0}
0z
1|
b110 $
b110 '
#80
0_
0`
0[
bx1001 "
bx1001 *
bx1001 U
1Z
08
1W
06
bx1001 (
bx1001 .
bx1001 S
13
b0z /
02
00
b11000 +
b11000 ,
0{
1z
b111 $
b111 '
#90
1F
1?
1C
0v
1>
0_
0g
0w
1o
17
0`
0h
0s
1p
b1000 "
b1000 *
b1000 U
0Z
1;
0[
0c
0O
1k
0W
16
08
0@
0P
1H
b1000 (
b1000 .
b1000 S
03
b111z /
12
19
1A
0L
0I
10
14
1<
0D
1{
1}
1!"
b111 +
b111 ,
0#"
0z
0|
0~
1""
b1000 $
b1000 '
#100
0o
0p
0k
1g
0H
1h
0F
1c
0?
1_
1@
0C
1`
0>
1[
07
b111 "
b111 *
b111 U
1Z
18
0;
1W
06
b111 (
b111 .
b111 S
13
b0z /
02
00
b110 +
b110 ,
0{
1z
b1001 $
b1001 '
#110
1_
1`
b110 "
b110 *
b110 U
0Z
1[
0W
16
18
b110 (
b110 .
b110 S
03
b1z /
12
09
10
04
1{
b101 +
b101 ,
0}
0z
1|
b1010 $
b1010 '
#120
0_
0`
0[
b101 "
b101 *
b101 U
1Z
08
1W
06
b101 (
b101 .
b101 S
13
b0z /
02
00
b100 +
b100 ,
0{
1z
b1011 $
b1011 '
#130
1>
0_
1g
17
0`
1h
b100 "
b100 *
b100 U
0Z
1;
0[
1c
0W
16
08
1@
b100 (
b100 .
b100 S
03
b11z /
12
19
0A
10
14
0<
1{
1}
b11 +
b11 ,
0!"
0z
0|
1~
b1100 $
b1100 '
#140
0g
0h
0c
1_
0@
1`
0>
1[
07
b11 "
b11 *
b11 U
1Z
18
0;
1W
06
b11 (
b11 .
b11 S
13
b0z /
02
00
b10 +
b10 ,
0{
1z
b1101 $
b1101 '
#150
1_
1`
b10 "
b10 *
b10 U
0Z
1[
0W
16
18
b10 (
b10 .
b10 S
03
b1z /
12
09
10
04
1{
b1 +
b1 ,
0}
0z
1|
b1110 $
b1110 '
#160
0_
0`
0[
b1 "
b1 *
b1 U
1Z
08
1W
06
b1 (
b1 .
b1 S
13
b0z /
02
00
b0 +
b0 ,
0{
1z
b1111 $
b1111 '
#170
x!
1R
1N
1G
1K
1F
1?
1C
xv
1>
0g
xw
0o
17
0`
0h
xs
0p
1;
0[
0c
0O
0k
0W
16
08
0@
1P
0H
bx0000 (
bx0000 .
bx0000 S
03
b1111z /
12
19
1A
1L
1I
10
14
1<
1D
0_
1{
1}
1!"
b11111 +
b11111 ,
1#"
0]
bx0001 "
bx0001 *
bx0001 U
1Z
b0z V
0Y
0z
0|
0~
0""
1X
b0 $
b0 '
b1 &
b1 T
b1 #
#180
xy
1u
x!
1n
1O
0R
1r
1p
0N
1m
1k
0G
1f
1H
0K
1j
1h
0F
1e
1c
0?
1^
1@
0C
1b
1`
0>
1]
1[
07
bx0000 "
bx0000 *
bx0000 U
0Z
b1111z V
1Y
18
0;
1W
06
bx1111 (
bx1111 .
bx1111 S
13
b0z /
02
00
b11110 +
b11110 ,
0{
1z
b1 $
b1 '
#190
0!
0y
0u
0n
1o
0r
0m
0f
1g
0j
0e
1_
0^
0b
0]
1`
bx1111 "
bx1111 *
bx1111 U
1Z
b0z V
0Y
1[
0W
16
18
bx1110 (
bx1110 .
bx1110 S
03
b1z /
12
09
10
04
1{
b11101 +
b11101 ,
0}
0z
1|
b10 $
b10 '
#200
0`
1]
0[
bx1110 "
bx1110 *
bx1110 U
0Z
b1z V
1Y
08
1W
06
bx1101 (
bx1101 .
bx1101 S
13
b0z /
02
00
b11100 +
b11100 ,
0{
1z
b11 $
b11 '
#210
0_
1>
1g
0]
17
0`
1h
bx1101 "
bx1101 *
bx1101 U
1Z
b0z V
0Y
1;
0[
1c
0W
16
08
1@
bx1100 (
bx1100 .
bx1100 S
03
b11z /
12
19
0A
10
14
0<
1{
1}
b11011 +
b11011 ,
0!"
0z
0|
1~
b100 $
b100 '
#220
0h
1e
0c
1^
0@
1b
1`
0>
1]
1[
07
bx1100 "
bx1100 *
bx1100 U
0Z
b11z V
1Y
18
0;
1W
06
bx1011 (
bx1011 .
bx1011 S
13
b0z /
02
00
b11010 +
b11010 ,
0{
1z
b101 $
b101 '
#230
0g
0e
1_
0^
0b
0]
1`
bx1011 "
bx1011 *
bx1011 U
1Z
b0z V
0Y
1[
0W
16
18
bx1010 (
bx1010 .
bx1010 S
03
b1z /
12
09
10
04
1{
b11001 +
b11001 ,
0}
0z
1|
b110 $
b110 '
#240
0`
1]
0[
bx1010 "
bx1010 *
bx1010 U
0Z
b1z V
1Y
08
1W
06
bx1001 (
bx1001 .
bx1001 S
13
b0z /
02
00
b11000 +
b11000 ,
0{
1z
b111 $
b111 '
#250
1F
1?
0_
1C
0v
1>
0g
0w
1o
0]
17
0`
0h
0s
1p
b1001 "
b1001 *
b1001 U
1Z
b0z V
0Y
1;
0[
0c
0O
1k
0W
16
08
0@
0P
1H
b1000 (
b1000 .
b1000 S
03
b111z /
12
19
1A
0L
0I
10
14
1<
0D
1{
1}
1!"
b111 +
b111 ,
0#"
0z
0|
0~
1""
b1000 $
b1000 '
#260
0p
1m
0k
1f
0H
1j
1h
0F
1e
1c
0?
1^
1@
0C
1b
1`
0>
1]
1[
07
b1000 "
b1000 *
b1000 U
0Z
b111z V
1Y
18
0;
1W
06
b111 (
b111 .
b111 S
13
b0z /
02
00
b110 +
b110 ,
0{
1z
b1001 $
b1001 '
#270
0o
0m
0f
1g
0j
0e
1_
0^
0b
0]
1`
b111 "
b111 *
b111 U
1Z
b0z V
0Y
1[
0W
16
18
b110 (
b110 .
b110 S
03
b1z /
12
09
10
04
1{
b101 +
b101 ,
0}
0z
1|
b1010 $
b1010 '
#280
0`
1]
0[
b110 "
b110 *
b110 U
0Z
b1z V
1Y
08
1W
06
b101 (
b101 .
b101 S
13
b0z /
02
00
b100 +
b100 ,
0{
1z
b1011 $
b1011 '
#290
0_
1>
1g
0]
17
0`
1h
b101 "
b101 *
b101 U
1Z
b0z V
0Y
1;
0[
1c
0W
16
08
1@
b100 (
b100 .
b100 S
03
b11z /
12
19
0A
10
14
0<
1{
1}
b11 +
b11 ,
0!"
0z
0|
1~
b1100 $
b1100 '
#300
0h
1e
0c
1^
0@
1b
1`
0>
1]
1[
07
b100 "
b100 *
b100 U
0Z
b11z V
1Y
18
0;
1W
06
b11 (
b11 .
b11 S
13
b0z /
02
00
b10 +
b10 ,
0{
1z
b1101 $
b1101 '
#310
0g
0e
1_
0^
0b
0]
1`
b11 "
b11 *
b11 U
1Z
b0z V
0Y
1[
0W
16
18
b10 (
b10 .
b10 S
03
b1z /
12
09
10
04
1{
b1 +
b1 ,
0}
0z
1|
b1110 $
b1110 '
#320
0`
1]
0[
b10 "
b10 *
b10 U
0Z
b1z V
1Y
08
1W
06
b1 (
b1 .
b1 S
13
b0z /
02
00
b0 +
b0 ,
0{
1z
b1111 $
b1111 '
#330
x!
0y
1R
0u
1N
0n
1G
0r
1K
0m
1F
0f
1?
0j
1C
xv
1>
xw
0o
17
0a
0h
xs
0p
1;
0[
0c
0O
0k
0W
16
08
0@
1P
0H
0g
bx0000 (
bx0000 .
bx0000 S
03
b1111z /
12
19
1A
1L
1I
0e
10
14
1<
1D
0^
1{
1}
1!"
b11111 +
b11111 ,
1#"
0]
1_
0b
bx0010 "
bx0010 *
bx0010 U
0Z
b0z V
0Y
1`
0z
0|
0~
0""
0X
1\
b0 $
b0 '
b10 &
b10 T
b10 #
#340
xy
1u
x!
1n
1O
0R
1r
1p
0N
1m
1k
0G
1f
1H
0K
1j
1h
0F
1e
1c
0?
0_
b1110z V
1^
1@
0C
0`
1a
0>
1[
07
bx0001 "
bx0001 *
bx0001 U
1Z
18
0;
1W
06
bx1111 (
bx1111 .
bx1111 S
13
b0z /
02
00
b11110 +
b11110 ,
0{
1z
b1 $
b1 '
#350
x!
xy
1u
1n
0o
1r
1m
1f
0g
1j
1e
0_
b1110z V
1^
0`
1a
bx0000 "
bx0000 *
bx0000 U
0Z
1[
0W
16
18
bx1110 (
bx1110 .
bx1110 S
03
b1z /
12
09
10
04
1{
b11101 +
b11101 ,
0}
0z
1|
b10 $
b10 '
#360
0!
0y
0u
0n
1o
0r
0m
0f
1g
0j
0e
1_
b0z V
0^
1`
0a
0[
bx1111 "
bx1111 *
bx1111 U
1Z
08
1W
06
bx1101 (
bx1101 .
bx1101 S
13
b0z /
02
00
b11100 +
b11100 ,
0{
1z
b11 $
b11 '
#370
0e
1>
1_
b0z V
0^
1g
17
1`
0a
1h
bx1110 "
bx1110 *
bx1110 U
0Z
1;
0[
1c
0W
16
08
1@
bx1100 (
bx1100 .
bx1100 S
03
b11z /
12
19
0A
10
14
0<
1{
1}
b11011 +
b11011 ,
0!"
0z
0|
1~
b100 $
b100 '
#380
0h
1e
0c
0_
b10z V
1^
0@
0`
1a
0>
1[
07
bx1101 "
bx1101 *
bx1101 U
1Z
18
0;
1W
06
bx1011 (
bx1011 .
bx1011 S
13
b0z /
02
00
b11010 +
b11010 ,
0{
1z
b101 $
b101 '
#390
1g
1e
0_
b10z V
1^
0`
1a
bx1100 "
bx1100 *
bx1100 U
0Z
1[
0W
16
18
bx1010 (
bx1010 .
bx1010 S
03
b1z /
12
09
10
04
1{
b11001 +
b11001 ,
0}
0z
1|
b110 $
b110 '
#400
0g
0e
1_
b0z V
0^
1`
0a
0[
bx1011 "
bx1011 *
bx1011 U
1Z
08
1W
06
bx1001 (
bx1001 .
bx1001 S
13
b0z /
02
00
b11000 +
b11000 ,
0{
1z
b111 $
b111 '
#410
0m
1F
0f
1?
0j
1C
0e
0v
1>
1_
b0z V
0^
0g
0w
1o
17
1`
0a
0h
0s
1p
b1010 "
b1010 *
b1010 U
0Z
1;
0[
0c
0O
1k
0W
16
08
0@
0P
1H
b1000 (
b1000 .
b1000 S
03
b111z /
12
19
1A
0L
0I
10
14
1<
0D
1{
1}
1!"
b111 +
b111 ,
0#"
0z
0|
0~
1""
b1000 $
b1000 '
#420
0p
1m
0k
1f
0H
1j
1h
0F
1e
1c
0?
0_
b110z V
1^
1@
0C
0`
1a
0>
1[
07
b1001 "
b1001 *
b1001 U
1Z
18
0;
1W
06
b111 (
b111 .
b111 S
13
b0z /
02
00
b110 +
b110 ,
0{
1z
b1001 $
b1001 '
#430
1o
1m
1f
0g
1j
1e
0_
b110z V
1^
0`
1a
b1000 "
b1000 *
b1000 U
0Z
1[
0W
16
18
b110 (
b110 .
b110 S
03
b1z /
12
09
10
04
1{
b101 +
b101 ,
0}
0z
1|
b1010 $
b1010 '
#440
0o
0m
0f
1g
0j
0e
1_
b0z V
0^
1`
0a
0[
b111 "
b111 *
b111 U
1Z
08
1W
06
b101 (
b101 .
b101 S
13
b0z /
02
00
b100 +
b100 ,
0{
1z
b1011 $
b1011 '
#450
0e
1>
1_
b0z V
0^
1g
17
1`
0a
1h
b110 "
b110 *
b110 U
0Z
1;
0[
1c
0W
16
08
1@
b100 (
b100 .
b100 S
03
b11z /
12
19
0A
10
14
0<
1{
1}
b11 +
b11 ,
0!"
0z
0|
1~
b1100 $
b1100 '
#460
0h
1e
0c
0_
b10z V
1^
0@
0`
1a
0>
1[
07
b101 "
b101 *
b101 U
1Z
18
0;
1W
06
b11 (
b11 .
b11 S
13
b0z /
02
00
b10 +
b10 ,
0{
1z
b1101 $
b1101 '
#470
1g
1e
0_
b10z V
1^
0`
1a
b100 "
b100 *
b100 U
0Z
1[
0W
16
18
b10 (
b10 .
b10 S
03
b1z /
12
09
10
04
1{
b1 +
b1 ,
0}
0z
1|
b1110 $
b1110 '
#480
0g
0e
1_
b0z V
0^
1`
0a
0[
b11 "
b11 *
b11 U
1Z
08
1W
06
b1 (
b1 .
b1 S
13
b0z /
02
00
b0 +
b0 ,
0{
1z
b1111 $
b1111 '
#490
1R
x!
1N
0y
1G
0u
1K
0n
1F
0r
1?
0m
1C
0f
xv
1>
0j
xw
0o
17
1`
0a
0h
xs
0p
1;
0[
0c
0O
0k
0g
0W
16
08
0@
1P
0H
0e
bx0000 (
bx0000 .
bx0000 S
03
b1111z /
12
19
1A
1L
1I
0^
10
14
1<
1D
1_
0b
1{
1}
1!"
b11111 +
b11111 ,
1#"
0]
bx0011 "
bx0011 *
bx0011 U
1Z
b0z V
0Y
0z
0|
0~
0""
1X
b0 $
b0 '
b11 &
b11 T
b11 #
#500
xy
1u
x!
1n
1O
0R
1r
1p
0N
1m
1k
0G
1f
1H
0K
1j
1h
0F
1e
1c
0?
1^
1@
0C
0`
1a
0>
1]
1[
07
bx0010 "
bx0010 *
bx0010 U
0Z
b1111z V
1Y
18
0;
1W
06
bx1111 (
bx1111 .
bx1111 S
13
b0z /
02
00
b11110 +
b11110 ,
0{
1z
b1 $
b1 '
#510
x!
xy
1u
1n
0o
1r
1m
1f
0g
1j
0_
1e
1^
0]
0`
1a
bx0001 "
bx0001 *
bx0001 U
1Z
b1110z V
0Y
1[
0W
16
18
bx1110 (
bx1110 .
bx1110 S
03
b1z /
12
09
10
04
1{
b11101 +
b11101 ,
0}
0z
1|
b10 $
b10 '
#520
1b
1`
0a
1]
0[
bx0000 "
bx0000 *
bx0000 U
0Z
b1111z V
1Y
08
1W
06
bx1101 (
bx1101 .
bx1101 S
13
b0z /
02
00
b11100 +
b11100 ,
0{
1z
b11 $
b11 '
#530
0!
0y
0u
0n
1o
0r
0e
0m
1_
0^
0f
1>
0b
1g
0j
0]
17
1`
0a
1h
bx1111 "
bx1111 *
bx1111 U
1Z
b0z V
0Y
1;
0[
1c
0W
16
08
1@
bx1100 (
bx1100 .
bx1100 S
03
b11z /
12
19
0A
10
14
0<
1{
1}
b11011 +
b11011 ,
0!"
0z
0|
1~
b100 $
b100 '
#540
0h
1e
0c
1^
0@
0`
1a
0>
1]
1[
07
bx1110 "
bx1110 *
bx1110 U
0Z
b11z V
1Y
18
0;
1W
06
bx1011 (
bx1011 .
bx1011 S
13
b0z /
02
00
b11010 +
b11010 ,
0{
1z
b101 $
b101 '
#550
1g
0_
1e
1^
0]
0`
1a
bx1101 "
bx1101 *
bx1101 U
1Z
b10z V
0Y
1[
0W
16
18
bx1010 (
bx1010 .
bx1010 S
03
b1z /
12
09
10
04
1{
b11001 +
b11001 ,
0}
0z
1|
b110 $
b110 '
#560
1b
1`
0a
1]
0[
bx1100 "
bx1100 *
bx1100 U
0Z
b11z V
1Y
08
1W
06
bx1001 (
bx1001 .
bx1001 S
13
b0z /
02
00
b11000 +
b11000 ,
0{
1z
b111 $
b111 '
#570
1F
1?
0e
0m
1_
1C
0^
0f
0v
1>
0b
0g
0j
0w
1o
0]
17
1`
0a
0h
0s
1p
b1011 "
b1011 *
b1011 U
1Z
b0z V
0Y
1;
0[
0c
0O
1k
0W
16
08
0@
0P
1H
b1000 (
b1000 .
b1000 S
03
b111z /
12
19
1A
0L
0I
10
14
1<
0D
1{
1}
1!"
b111 +
b111 ,
0#"
0z
0|
0~
1""
b1000 $
b1000 '
#580
0p
1m
0k
1f
0H
1j
1h
0F
1e
1c
0?
1^
1@
0C
0`
1a
0>
1]
1[
07
b1010 "
b1010 *
b1010 U
0Z
b111z V
1Y
18
0;
1W
06
b111 (
b111 .
b111 S
13
b0z /
02
00
b110 +
b110 ,
0{
1z
b1001 $
b1001 '
#590
1o
1m
1f
0g
1j
0_
1e
1^
0]
0`
1a
b1001 "
b1001 *
b1001 U
1Z
b110z V
0Y
1[
0W
16
18
b110 (
b110 .
b110 S
03
b1z /
12
09
10
04
1{
b101 +
b101 ,
0}
0z
1|
b1010 $
b1010 '
#600
1b
1`
0a
1]
0[
b1000 "
b1000 *
b1000 U
0Z
b111z V
1Y
08
1W
06
b101 (
b101 .
b101 S
13
b0z /
02
00
b100 +
b100 ,
0{
1z
b1011 $
b1011 '
#610
0o
0e
0m
1_
0^
0f
1>
0b
1g
0j
0]
17
1`
0a
1h
b111 "
b111 *
b111 U
1Z
b0z V
0Y
1;
0[
1c
0W
16
08
1@
b100 (
b100 .
b100 S
03
b11z /
12
19
0A
10
14
0<
1{
1}
b11 +
b11 ,
0!"
0z
0|
1~
b1100 $
b1100 '
#620
0h
1e
0c
1^
0@
0`
1a
0>
1]
1[
07
b110 "
b110 *
b110 U
0Z
b11z V
1Y
18
0;
1W
06
b11 (
b11 .
b11 S
13
b0z /
02
00
b10 +
b10 ,
0{
1z
b1101 $
b1101 '
#630
1g
0_
1e
1^
0]
0`
1a
b101 "
b101 *
b101 U
1Z
b10z V
0Y
1[
0W
16
18
b10 (
b10 .
b10 S
03
b1z /
12
09
10
04
1{
b1 +
b1 ,
0}
0z
1|
b1110 $
b1110 '
#640
1b
1`
0a
1]
0[
b100 "
b100 *
b100 U
0Z
b11z V
1Y
08
1W
06
b1 (
b1 .
b1 S
13
b0z /
02
00
b0 +
b0 ,
0{
1z
b1111 $
b1111 '
#650
1R
1N
x!
1G
0y
1K
0u
1F
0n
1?
0r
1C
xv
1>
xw
17
0i
xs
0p
1;
0[
0c
0O
0k
0W
16
08
0@
1P
0H
0o
bx0000 (
bx0000 .
bx0000 S
03
b1111z /
12
19
1A
1L
1I
0e
0m
10
14
1<
1D
0^
0f
1{
1}
1!"
b11111 +
b11111 ,
1#"
0]
0_
0b
1g
0j
bx0100 "
bx0100 *
bx0100 U
0Z
b0z V
0Y
0`
1h
0z
0|
0~
0""
0X
0\
1d
b0 $
b0 '
b100 &
b100 T
b100 #
#660
xy
1u
x!
1n
1O
0R
1r
1p
0N
1m
1k
0G
0g
b1100z V
1f
1H
0K
0h
1i
0F
1c
0?
1_
1@
0C
1`
0>
1[
07
bx0011 "
bx0011 *
bx0011 U
1Z
18
0;
1W
06
bx1111 (
bx1111 .
bx1111 S
13
b0z /
02
00
b11110 +
b11110 ,
0{
1z
b1 $
b1 '
#670
1_
1`
bx0010 "
bx0010 *
bx0010 U
0Z
1[
0W
16
18
bx1110 (
bx1110 .
bx1110 S
03
b1z /
12
09
10
04
1{
b11101 +
b11101 ,
0}
0z
1|
b10 $
b10 '
#680
0_
0`
0[
bx0001 "
bx0001 *
bx0001 U
1Z
08
1W
06
bx1101 (
bx1101 .
bx1101 S
13
b0z /
02
00
b11100 +
b11100 ,
0{
1z
b11 $
b11 '
#690
x!
xy
1u
1n
0o
1r
1m
1>
0_
0g
b1100z V
1f
17
0`
0h
1i
bx0000 "
bx0000 *
bx0000 U
0Z
1;
0[
1c
0W
16
08
1@
bx1100 (
bx1100 .
bx1100 S
03
b11z /
12
19
0A
10
14
0<
1{
1}
b11011 +
b11011 ,
0!"
0z
0|
1~
b100 $
b100 '
#700
0!
0y
0u
0n
1o
0r
0m
1g
b0z V
0f
1h
0i
0c
1_
0@
1`
0>
1[
07
bx1111 "
bx1111 *
bx1111 U
1Z
18
0;
1W
06
bx1011 (
bx1011 .
bx1011 S
13
b0z /
02
00
b11010 +
b11010 ,
0{
1z
b101 $
b101 '
#710
1_
1`
bx1110 "
bx1110 *
bx1110 U
0Z
1[
0W
16
18
bx1010 (
bx1010 .
bx1010 S
03
b1z /
12
09
10
04
1{
b11001 +
b11001 ,
0}
0z
1|
b110 $
b110 '
#720
0_
0`
0[
bx1101 "
bx1101 *
bx1101 U
1Z
08
1W
06
bx1001 (
bx1001 .
bx1001 S
13
b0z /
02
00
b11000 +
b11000 ,
0{
1z
b111 $
b111 '
#730
1F
1?
1C
0m
0v
1>
0_
1g
b0z V
0f
0w
1o
17
0`
1h
0i
0s
1p
b1100 "
b1100 *
b1100 U
0Z
1;
0[
0c
0O
1k
0W
16
08
0@
0P
1H
b1000 (
b1000 .
b1000 S
03
b111z /
12
19
1A
0L
0I
10
14
1<
0D
1{
1}
1!"
b111 +
b111 ,
0#"
0z
0|
0~
1""
b1000 $
b1000 '
#740
0p
1m
0k
0g
b100z V
1f
0H
0h
1i
0F
1c
0?
1_
1@
0C
1`
0>
1[
07
b1011 "
b1011 *
b1011 U
1Z
18
0;
1W
06
b111 (
b111 .
b111 S
13
b0z /
02
00
b110 +
b110 ,
0{
1z
b1001 $
b1001 '
#750
1_
1`
b1010 "
b1010 *
b1010 U
0Z
1[
0W
16
18
b110 (
b110 .
b110 S
03
b1z /
12
09
10
04
1{
b101 +
b101 ,
0}
0z
1|
b1010 $
b1010 '
#760
0_
0`
0[
b1001 "
b1001 *
b1001 U
1Z
08
1W
06
b101 (
b101 .
b101 S
13
b0z /
02
00
b100 +
b100 ,
0{
1z
b1011 $
b1011 '
