Exp10/T3/modules.v
module five_bit(a,b,s,cout);

input [4:0] a,b;
output [4:0] s,c;
output cout;

ha b1(a[0],b[0],s[0],c[1]);
fa b2(a[1],b[1],c[1],s[1],c[2]);
fa b3(a[2],b[2],c[2],s[2],c[3]);
fa b4(a[3],b[3],c[3],s[3],c[4]);
fa b5(a[4],b[4],c[4],s[4],cout);

endmodule

module comp(s,a,out);

input s,a;
output out;

assign out = ~(s ^ a);


endmodule

module ha(a , b, sum , carry);

input a,b;
output sum,carry;

xor x1 (sum , a ,b ) ;
and a1 ( carry , a , b ) ;

endmodule

module fa(a , b , carryin , sum , carryout);

input a,b,carryin;
output sum,carryout;
wire w1,w2,w3;

xor x1 ( w1 , a ,b ) ;
and a1 ( w2 , a , b ) ;
xor x2 ( sum , carryin , w1 );
and a2 ( w3 , w1 , carryin );
or  o3 ( carryout , w2 ,w3 );

endmodule

Exp10/T3/exp.v
module t3(a,b,s,sum2,cout);

input [3:0] a,b;
input s;
wire [4:0] c,d,tmp;
output [4:0] sum,sum2;
output cout;

comp s0(s,b[0],c[0]);
comp s1(s,b[1],c[1]);
comp s2(s,b[2],c[2]);
comp s3(s,b[3],c[3]);
assign c[4] = c[3];

assign tmp[0]=~s;
assign tmp[1]=0;
assign tmp[2]=0;
assign tmp[3]=0;
assign tmp[4]=0;

assign d[0]=a[0];
assign d[1]=a[1];
assign d[2]=a[2];
assign d[3]=a[3];
assign d[4]=a[3];

five_bit fb1(c,tmp,sum,cout);

five_bit fb2(sum,d,sum2,cout);


endmodule

Exp10/T3/test02.v
module test_four_bit_adder;                 //test bench module                            //outputs from full adder
reg [3:0] a,b;
reg s;
wire [4:0]sum2;
wire cout;                    //inputs to the full adder adder module
t3 DUT(a,b,s,sum2,cout);           //instantiate the device under test (5 bit adder)
initial
begin
$dumpfile("testfive.vcd");
$dumpvars(0,test_four_bit_adder);
$monitor("At time = %t,a = %b,b = %b,s = %b,output= %b",$time,a,b,s,sum2);
#10 a = 4'b0000; b = 4'b0000; s = 1'b0;
#10 a = 4'b0000; b = 4'b0001; s = 1'b0;
#10 a = 4'b0000; b = 4'b0010; s = 1'b0;
#10 a = 4'b1111; b = 4'b0111; s = 1'b1;
#10 a = 4'b1111; b = 4'b1000; s = 1'b1;
#10 a = 4'b1111; b = 4'b1001; s = 1'b1;
#10 a = 4'b1111; b = 4'b1010; s = 1'b1;
#10 a = 4'b1111; b = 4'b1011; s = 1'b1;
#10 a = 4'b1111; b = 4'b1100; s = 1'b1;
#10 a = 4'b1111; b = 4'b1101; s = 1'b1;
#10 a = 4'b1111; b = 4'b1110; s = 1'b1;
#10 a = 4'b1111; b = 4'b1111; s = 1'b1;

#10 $finish;
end
endmodule

Exp10/T3/testfive.vcd
$date
	Tue Jan 29 15:59:55 2019
$end
$version
	Icarus Verilog
$end
$timescale
	1s
$end
$scope module test_four_bit_adder $end
$var wire 1 ! cout $end
$var wire 5 " sum2 [4:0] $end
$var reg 4 # a [3:0] $end
$var reg 4 $ b [3:0] $end
$var reg 1 % s $end
$scope module DUT $end
$var wire 4 & a [3:0] $end
$var wire 4 ' b [3:0] $end
$var wire 1 ! cout $end
$var wire 1 % s $end
$var wire 5 ( tmp [4:0] $end
$var wire 5 ) sum2 [4:0] $end
$var wire 5 * sum [4:0] $end
$var wire 5 + d [4:0] $end
$var wire 5 , c [4:0] $end
$scope module fb1 $end
$var wire 5 - a [4:0] $end
$var wire 5 . b [4:0] $end
$var wire 1 ! cout $end
$var wire 5 / s [4:0] $end
$var wire 5 0 c [4:0] $end
$scope module b1 $end
$var wire 1 1 a $end
$var wire 1 2 b $end
$var wire 1 3 carry $end
$var wire 1 4 sum $end
$upscope $end
$scope module b2 $end
$var wire 1 5 a $end
$var wire 1 6 b $end
$var wire 1 7 carryin $end
$var wire 1 8 carryout $end
$var wire 1 9 sum $end
$var wire 1 : w1 $end
$var wire 1 ; w2 $end
$var wire 1 < w3 $end
$upscope $end
$scope module b3 $end
$var wire 1 = a $end
$var wire 1 > b $end
$var wire 1 ? carryin $end
$var wire 1 @ carryout $end
$var wire 1 A sum $end
$var wire 1 B w1 $end
$var wire 1 C w2 $end
$var wire 1 D w3 $end
$upscope $end
$scope module b4 $end
$var wire 1 E a $end
$var wire 1 F b $end
$var wire 1 G carryin $end
$var wire 1 H carryout $end
$var wire 1 I sum $end
$var wire 1 J w1 $end
$var wire 1 K w2 $end
$var wire 1 L w3 $end
$upscope $end
$scope module b5 $end
$var wire 1 M a $end
$var wire 1 N b $end
$var wire 1 O carryin $end
$var wire 1 ! carryout $end
$var wire 1 P sum $end
$var wire 1 Q w1 $end
$var wire 1 R w2 $end
$var wire 1 S w3 $end
$upscope $end
$upscope $end
$scope module fb2 $end
$var wire 5 T a [4:0] $end
$var wire 5 U b [4:0] $end
$var wire 1 ! cout $end
$var wire 5 V s [4:0] $end
$var wire 5 W c [4:0] $end
$scope module b1 $end
$var wire 1 X a $end
$var wire 1 Y b $end
$var wire 1 Z carry $end
$var wire 1 [ sum $end
$upscope $end
$scope module b2 $end
$var wire 1 \ a $end
$var wire 1 ] b $end
$var wire 1 ^ carryin $end
$var wire 1 _ carryout $end
$var wire 1 ` sum $end
$var wire 1 a w1 $end
$var wire 1 b w2 $end
$var wire 1 c w3 $end
$upscope $end
$scope module b3 $end
$var wire 1 d a $end
$var wire 1 e b $end
$var wire 1 f carryin $end
$var wire 1 g carryout $end
$var wire 1 h sum $end
$var wire 1 i w1 $end
$var wire 1 j w2 $end
$var wire 1 k w3 $end
$upscope $end
$scope module b4 $end
$var wire 1 l a $end
$var wire 1 m b $end
$var wire 1 n carryin $end
$var wire 1 o carryout $end
$var wire 1 p sum $end
$var wire 1 q w1 $end
$var wire 1 r w2 $end
$var wire 1 s w3 $end
$upscope $end
$scope module b5 $end
$var wire 1 t a $end
$var wire 1 u b $end
$var wire 1 v carryin $end
$var wire 1 ! carryout $end
$var wire 1 w sum $end
$var wire 1 x w1 $end
$var wire 1 y w2 $end
$var wire 1 z w3 $end
$upscope $end
$upscope $end
$scope module s0 $end
$var wire 1 { a $end
$var wire 1 | out $end
$var wire 1 % s $end
$upscope $end
$scope module s1 $end
$var wire 1 } a $end
$var wire 1 ~ out $end
$var wire 1 % s $end
$upscope $end
$scope module s2 $end
$var wire 1 !" a $end
$var wire 1 "" out $end
$var wire 1 % s $end
$upscope $end
$scope module s3 $end
$var wire 1 #" a $end
$var wire 1 $" out $end
$var wire 1 % s $end
$upscope $end
$upscope $end
$upscope $end
$enddefinitions $end
#0
$dumpvars
x$"
x#"
x""
x!"
x~
x}
x|
x{
xz
xy
xx
xw
xv
xu
xt
xs
xr
xq
xp
xo
xn
xm
xl
xk
xj
xi
xh
xg
xf
xe
xd
xc
xb
xa
x`
x_
x^
x]
x\
x[
xZ
xY
xX
bxz W
bx V
bx U
bx T
xS
0R
xQ
xP
xO
0N
xM
xL
0K
xJ
xI
xH
xG
0F
xE
xD
0C
xB
xA
x@
x?
0>
x=
x<
0;
x:
x9
x8
x7
06
x5
x4
x3
x2
x1
bxz 0
bx /
b0x .
bx -
bx ,
bx +
bx *
bx )
b0x (
bx '
bx &
x%
bx $
bx #
bx "
x!
$end
#10
0w
0x
0t
0p
0P
1S
0z
0q
1O
0v
0l
1H
0o
0h
0I
1L
0s
0i
1G
0n
0d
1@
0g
0`
0A
1D
0k
0a
1?
0f
0\
18
0_
b0 "
b0 )
b0 V
0[
09
1<
1Q
0c
0X
17
1:
1B
1M
1J
0^
b0 *
b0 /
b0 T
04
b1111z 0
13
11
15
1=
1E
b0z W
0Z
0b
0j
0r
0y
12
1|
1~
1""
b11111 ,
b11111 -
1$"
0Y
0]
0e
0m
0u
b1 (
b1 .
0{
0}
0!"
0#"
b0 +
b0 U
0%
b0 $
b0 '
b0 #
b0 &
#20
1w
1x
1t
0!
1p
1P
0S
1q
0O
1l
0H
1h
1I
0L
1i
0G
1d
0@
1`
1A
0D
1a
0?
1\
08
b11111 "
b11111 )
b11111 V
1[
19
0<
1X
07
b11111 *
b11111 /
b11111 T
14
b0z 0
03
01
b11110 ,
b11110 -
0|
1{
b1 $
b1 '
#30
1`
1a
b11110 "
b11110 )
b11110 V
0[
1\
0X
17
19
b11110 *
b11110 /
b11110 T
04
b1z 0
13
0:
11
05
1|
b11101 ,
b11101 -
0~
0{
1}
b10 $
b10 '
#40
0`
0a
0\
b11101 "
b11101 )
b11101 V
1[
09
1X
07
b11101 *
b11101 /
b11101 T
14
b0z 0
03
01
b11100 ,
b11100 -
0|
1{
b11 $
b11 '
#50
1?
0`
1h
18
0a
1i
b11100 "
b11100 )
b11100 V
0[
1<
0\
1d
0X
17
09
1A
b11100 *
b11100 /
b11100 T
04
b11z 0
13
1:
0B
11
15
0=
1|
1~
b11011 ,
b11011 -
0""
0{
0}
1!"
b100 $
b100 '
#60
0h
0i
0d
1`
0A
1a
0?
1\
08
b11011 "
b11011 )
b11011 V
1[
19
0<
1X
07
b11011 *
b11011 /
b11011 T
14
b0z 0
03
01
b11010 ,
b11010 -
0|
1{
b101 $
b101 '
#70
1`
1a
b11010 "
b11010 )
b11010 V
0[
1\
0X
17
19
b11010 *
b11010 /
b11010 T
04
b1z 0
13
0:
11
05
1|
b11001 ,
b11001 -
0~
0{
1}
b110 $
b110 '
#80
0`
0a
0\
b11001 "
b11001 )
b11001 V
1[
09
1X
07
b11001 *
b11001 /
b11001 T
14
b0z 0
03
01
b11000 ,
b11000 -
0|
1{
b111 $
b111 '
#90
1G
1@
1D
0w
1?
0`
0h
0x
1p
18
0a
0i
0t
1q
b1000 "
b1000 )
b1000 V
0[
1<
0\
0d
0P
1l
0X
17
09
0A
0Q
1I
b1000 *
b1000 /
b1000 T
04
b111z 0
13
1:
1B
0M
0J
11
15
1=
0E
1|
1~
1""
b111 ,
b111 -
0$"
0{
0}
0!"
1#"
b1000 $
b1000 '
#100
0p
0q
0l
1h
0I
1i
0G
1d
0@
1`
1A
0D
1a
0?
1\
08
b111 "
b111 )
b111 V
1[
19
0<
1X
07
b111 *
b111 /
b111 T
14
b0z 0
03
01
b110 ,
b110 -
0|
1{
b1001 $
b1001 '
#110
1`
1a
b110 "
b110 )
b110 V
0[
1\
0X
17
19
b110 *
b110 /
b110 T
04
b1z 0
13
0:
11
05
1|
b101 ,
b101 -
0~
0{
1}
b1010 $
b1010 '
#120
0`
0a
0\
b101 "
b101 )
b101 V
1[
09
1X
07
b101 *
b101 /
b101 T
14
b0z 0
03
01
b100 ,
b100 -
0|
1{
b1011 $
b1011 '
#130
1?
0`
1h
18
0a
1i
b100 "
b100 )
b100 V
0[
1<
0\
1d
0X
17
09
1A
b100 *
b100 /
b100 T
04
b11z 0
13
1:
0B
11
15
0=
1|
1~
b11 ,
b11 -
0""
0{
0}
1!"
b1100 $
b1100 '
#140
0h
0i
0d
1`
0A
1a
0?
1\
08
b11 "
b11 )
b11 V
1[
19
0<
1X
07
b11 *
b11 /
b11 T
14
b0z 0
03
01
b10 ,
b10 -
0|
1{
b1101 $
b1101 '
#150
1`
1a
b10 "
b10 )
b10 V
0[
1\
0X
17
19
b10 *
b10 /
b10 T
04
b1z 0
13
0:
11
05
1|
b1 ,
b1 -
0~
0{
1}
b1110 $
b1110 '
#160
0`
0a
0\
b1 "
b1 )
b1 V
1[
09
1X
07
b1 *
b1 /
b1 T
14
b0z 0
03
01
b0 ,
b0 -
0|
1{
b1111 $
b1111 '
#170
x!
1S
1O
1H
1L
1G
1@
1D
0w
1?
0h
0x
0p
18
0a
0i
0t
0q
1<
0\
0d
0P
0l
0X
17
09
0A
1Q
0I
b0 *
b0 /
b0 T
04
b1111z 0
13
1:
1B
1M
1J
0`
11
15
1=
1E
0^
1|
1~
1""
b11111 ,
b11111 -
1$"
b1 "
b1 )
b1 V
1[
b0z W
0Z
1Y
0{
0}
0!"
0#"
b1 +
b1 U
b0 $
b0 '
b1 #
b1 &
#180
1z
1x
1v
1t
x!
1o
1P
0S
1s
1q
0O
1n
1l
0H
1g
1I
0L
1k
1i
0G
1f
1d
0@
1_
1A
0D
1c
1a
0?
1^
1\
08
b0 "
b0 )
b0 V
0[
b1111z W
1Z
19
0<
1X
07
b11111 *
b11111 /
b11111 T
14
b0z 0
03
01
b11110 ,
b11110 -
0|
1{
b1 $
b1 '
#190
0!
1w
0z
0v
0o
1p
0s
0n
0g
1h
0k
0f
1`
0_
0c
0^
1a
b11111 "
b11111 )
b11111 V
1[
b0z W
0Z
1\
0X
17
19
b11110 *
b11110 /
b11110 T
04
b1z 0
13
0:
11
05
1|
b11101 ,
b11101 -
0~
0{
1}
b10 $
b10 '
#200
0a
1^
0\
b11110 "
b11110 )
b11110 V
0[
b1z W
1Z
09
1X
07
b11101 *
b11101 /
b11101 T
14
b0z 0
03
01
b11100 ,
b11100 -
0|
1{
b11 $
b11 '
#210
0`
1?
1h
0^
18
0a
1i
b11101 "
b11101 )
b11101 V
1[
b0z W
0Z
1<
0\
1d
0X
17
09
1A
b11100 *
b11100 /
b11100 T
04
b11z 0
13
1:
0B
11
15
0=
1|
1~
b11011 ,
b11011 -
0""
0{
0}
1!"
b100 $
b100 '
#220
0i
1f
0d
1_
0A
1c
1a
0?
1^
1\
08
b11100 "
b11100 )
b11100 V
0[
b11z W
1Z
19
0<
1X
07
b11011 *
b11011 /
b11011 T
14
b0z 0
03
01
b11010 ,
b11010 -
0|
1{
b101 $
b101 '
#230
0h
0f
1`
0_
0c
0^
1a
b11011 "
b11011 )
b11011 V
1[
b0z W
0Z
1\
0X
17
19
b11010 *
b11010 /
b11010 T
04
b1z 0
13
0:
11
05
1|
b11001 ,
b11001 -
0~
0{
1}
b110 $
b110 '
#240
0a
1^
0\
b11010 "
b11010 )
b11010 V
0[
b1z W
1Z
09
1X
07
b11001 *
b11001 /
b11001 T
14
b0z 0
03
01
b11000 ,
b11000 -
0|
1{
b111 $
b111 '
#250
1G
1@
0`
1D
0w
1?
0h
0x
1p
0^
18
0a
0i
0t
1q
b1001 "
b1001 )
b1001 V
1[
b0z W
0Z
1<
0\
0d
0P
1l
0X
17
09
0A
0Q
1I
b1000 *
b1000 /
b1000 T
04
b111z 0
13
1:
1B
0M
0J
11
15
1=
0E
1|
1~
1""
b111 ,
b111 -
0$"
0{
0}
0!"
1#"
b1000 $
b1000 '
#260
0q
1n
0l
1g
0I
1k
1i
0G
1f
1d
0@
1_
1A
0D
1c
1a
0?
1^
1\
08
b1000 "
b1000 )
b1000 V
0[
b111z W
1Z
19
0<
1X
07
b111 *
b111 /
b111 T
14
b0z 0
03
01
b110 ,
b110 -
0|
1{
b1001 $
b1001 '
#270
0p
0n
0g
1h
0k
0f
1`
0_
0c
0^
1a
b111 "
b111 )
b111 V
1[
b0z W
0Z
1\
0X
17
19
b110 *
b110 /
b110 T
04
b1z 0
13
0:
11
05
1|
b101 ,
b101 -
0~
0{
1}
b1010 $
b1010 '
#280
0a
1^
0\
b110 "
b110 )
b110 V
0[
b1z W
1Z
09
1X
07
b101 *
b101 /
b101 T
14
b0z 0
03
01
b100 ,
b100 -
0|
1{
b1011 $
b1011 '
#290
0`
1?
1h
0^
18
0a
1i
b101 "
b101 )
b101 V
1[
b0z W
0Z
1<
0\
1d
0X
17
09
1A
b100 *
b100 /
b100 T
04
b11z 0
13
1:
0B
11
15
0=
1|
1~
b11 ,
b11 -
0""
0{
0}
1!"
b1100 $
b1100 '
#300
0i
1f
0d
1_
0A
1c
1a
0?
1^
1\
08
b100 "
b100 )
b100 V
0[
b11z W
1Z
19
0<
1X
07
b11 *
b11 /
b11 T
14
b0z 0
03
01
b10 ,
b10 -
0|
1{
b1101 $
b1101 '
#310
0h
0f
1`
0_
0c
0^
1a
b11 "
b11 )
b11 V
1[
b0z W
0Z
1\
0X
17
19
b10 *
b10 /
b10 T
04
b1z 0
13
0:
11
05
1|
b1 ,
b1 -
0~
0{
1}
b1110 $
b1110 '
#320
0a
1^
0\
b10 "
b10 )
b10 V
0[
b1z W
1Z
09
1X
07
b1 *
b1 /
b1 T
14
b0z 0
03
01
b0 ,
b0 -
0|
1{
b1111 $
b1111 '
#330
x!
0z
1S
0v
1O
0o
1H
0s
1L
0n
1G
0g
1@
0k
1D
0w
1?
0x
0p
18
0b
0i
0t
0q
1<
0\
0d
0P
0l
0h
0X
17
09
0A
1Q
0I
0f
b0 *
b0 /
b0 T
04
b1111z 0
13
1:
1B
1M
1J
0_
11
15
1=
1E
0^
1`
0c
1|
1~
1""
b11111 ,
b11111 -
1$"
b10 "
b10 )
b10 V
0[
b0z W
0Z
1a
0Y
1]
0{
0}
0!"
0#"
b10 +
b10 U
b0 $
b0 '
b10 #
b10 &
#340
1z
1x
1v
1t
x!
1o
1P
0S
1s
1q
0O
1n
1l
0H
1g
1I
0L
1k
1i
0G
1f
1d
0@
0`
b1110z W
1_
1A
0D
0a
1b
0?
1\
08
b1 "
b1 )
b1 V
1[
19
0<
1X
07
b11111 *
b11111 /
b11111 T
14
b0z 0
03
01
b11110 ,
b11110 -
0|
1{
b1 $
b1 '
#350
x!
0w
1z
1v
1o
0p
1s
1n
1g
0h
1k
1f
0`
b1110z W
1_
0a
1b
b0 "
b0 )
b0 V
0[
1\
0X
17
19
b11110 *
b11110 /
b11110 T
04
b1z 0
13
0:
11
05
1|
b11101 ,
b11101 -
0~
0{
1}
b10 $
b10 '
#360
0!
1w
0z
0v
0o
1p
0s
0n
0g
1h
0k
0f
1`
b0z W
0_
1a
0b
0\
b11111 "
b11111 )
b11111 V
1[
09
1X
07
b11101 *
b11101 /
b11101 T
14
b0z 0
03
01
b11100 ,
b11100 -
0|
1{
b11 $
b11 '
#370
0f
1?
1`
b0z W
0_
1h
18
1a
0b
1i
b11110 "
b11110 )
b11110 V
0[
1<
0\
1d
0X
17
09
1A
b11100 *
b11100 /
b11100 T
04
b11z 0
13
1:
0B
11
15
0=
1|
1~
b11011 ,
b11011 -
0""
0{
0}
1!"
b100 $
b100 '
#380
0i
1f
0d
0`
b10z W
1_
0A
0a
1b
0?
1\
08
b11101 "
b11101 )
b11101 V
1[
19
0<
1X
07
b11011 *
b11011 /
b11011 T
14
b0z 0
03
01
b11010 ,
b11010 -
0|
1{
b101 $
b101 '
#390
1h
1f
0`
b10z W
1_
0a
1b
b11100 "
b11100 )
b11100 V
0[
1\
0X
17
19
b11010 *
b11010 /
b11010 T
04
b1z 0
13
0:
11
05
1|
b11001 ,
b11001 -
0~
0{
1}
b110 $
b110 '
#400
0h
0f
1`
b0z W
0_
1a
0b
0\
b11011 "
b11011 )
b11011 V
1[
09
1X
07
b11001 *
b11001 /
b11001 T
14
b0z 0
03
01
b11000 ,
b11000 -
0|
1{
b111 $
b111 '
#410
0n
1G
0g
1@
0k
1D
0f
0w
1?
1`
b0z W
0_
0h
0x
1p
18
1a
0b
0i
0t
1q
b1010 "
b1010 )
b1010 V
0[
1<
0\
0d
0P
1l
0X
17
09
0A
0Q
1I
b1000 *
b1000 /
b1000 T
04
b111z 0
13
1:
1B
0M
0J
11
15
1=
0E
1|
1~
1""
b111 ,
b111 -
0$"
0{
0}
0!"
1#"
b1000 $
b1000 '
#420
0q
1n
0l
1g
0I
1k
1i
0G
1f
1d
0@
0`
b110z W
1_
1A
0D
0a
1b
0?
1\
08
b1001 "
b1001 )
b1001 V
1[
19
0<
1X
07
b111 *
b111 /
b111 T
14
b0z 0
03
01
b110 ,
b110 -
0|
1{
b1001 $
b1001 '
#430
1p
1n
1g
0h
1k
1f
0`
b110z W
1_
0a
1b
b1000 "
b1000 )
b1000 V
0[
1\
0X
17
19
b110 *
b110 /
b110 T
04
b1z 0
13
0:
11
05
1|
b101 ,
b101 -
0~
0{
1}
b1010 $
b1010 '
#440
0p
0n
0g
1h
0k
0f
1`
b0z W
0_
1a
0b
0\
b111 "
b111 )
b111 V
1[
09
1X
07
b101 *
b101 /
b101 T
14
b0z 0
03
01
b100 ,
b100 -
0|
1{
b1011 $
b1011 '
#450
0f
1?
1`
b0z W
0_
1h
18
1a
0b
1i
b110 "
b110 )
b110 V
0[
1<
0\
1d
0X
17
09
1A
b100 *
b100 /
b100 T
04
b11z 0
13
1:
0B
11
15
0=
1|
1~
b11 ,
b11 -
0""
0{
0}
1!"
b1100 $
b1100 '
#460
0i
1f
0d
0`
b10z W
1_
0A
0a
1b
0?
1\
08
b101 "
b101 )
b101 V
1[
19
0<
1X
07
b11 *
b11 /
b11 T
14
b0z 0
03
01
b10 ,
b10 -
0|
1{
b1101 $
b1101 '
#470
1h
1f
0`
b10z W
1_
0a
1b
b100 "
b100 )
b100 V
0[
1\
0X
17
19
b10 *
b10 /
b10 T
04
b1z 0
13
0:
11
05
1|
b1 ,
b1 -
0~
0{
1}
b1110 $
b1110 '
#480
0h
0f
1`
b0z W
0_
1a
0b
0\
b11 "
b11 )
b11 V
1[
09
1X
07
b1 *
b1 /
b1 T
14
b0z 0
03
01
b0 ,
b0 -
0|
1{
b1111 $
b1111 '
#490
1S
x!
1O
0z
1H
0v
1L
0o
1G
0s
1@
0n
1D
0g
0w
1?
0k
0x
0p
18
1a
0b
0i
0t
0q
0h
1<
0\
0d
0P
0l
0f
0X
17
09
0A
1Q
0I
0_
b0 *
b0 /
b0 T
04
b1111z 0
13
1:
1B
1M
1J
1`
0c
11
15
1=
1E
0^
1|
1~
1""
b11111 ,
b11111 -
1$"
b11 "
b11 )
b11 V
1[
b0z W
0Z
1Y
0{
0}
0!"
0#"
b11 +
b11 U
b0 $
b0 '
b11 #
b11 &
#500
1z
1x
1v
1t
x!
1o
1P
0S
1s
1q
0O
1n
1l
0H
1g
1I
0L
1k
1i
0G
1f
1d
0@
1_
1A
0D
0a
1b
0?
1^
1\
08
b10 "
b10 )
b10 V
0[
b1111z W
1Z
19
0<
1X
07
b11111 *
b11111 /
b11111 T
14
b0z 0
03
01
b11110 ,
b11110 -
0|
1{
b1 $
b1 '
#510
x!
0w
1z
1v
1o
0p
1s
1n
1g
0h
1k
0`
1f
1_
0^
0a
1b
b1 "
b1 )
b1 V
1[
b1110z W
0Z
1\
0X
17
19
b11110 *
b11110 /
b11110 T
04
b1z 0
13
0:
11
05
1|
b11101 ,
b11101 -
0~
0{
1}
b10 $
b10 '
#520
1c
1a
0b
1^
0\
b0 "
b0 )
b0 V
0[
b1111z W
1Z
09
1X
07
b11101 *
b11101 /
b11101 T
14
b0z 0
03
01
b11100 ,
b11100 -
0|
1{
b11 $
b11 '
#530
0!
1w
0z
0v
0o
1p
0s
0f
0n
1`
0_
0g
1?
0c
1h
0k
0^
18
1a
0b
1i
b11111 "
b11111 )
b11111 V
1[
b0z W
0Z
1<
0\
1d
0X
17
09
1A
b11100 *
b11100 /
b11100 T
04
b11z 0
13
1:
0B
11
15
0=
1|
1~
b11011 ,
b11011 -
0""
0{
0}
1!"
b100 $
b100 '
#540
0i
1f
0d
1_
0A
0a
1b
0?
1^
1\
08
b11110 "
b11110 )
b11110 V
0[
b11z W
1Z
19
0<
1X
07
b11011 *
b11011 /
b11011 T
14
b0z 0
03
01
b11010 ,
b11010 -
0|
1{
b101 $
b101 '
#550
1h
0`
1f
1_
0^
0a
1b
b11101 "
b11101 )
b11101 V
1[
b10z W
0Z
1\
0X
17
19
b11010 *
b11010 /
b11010 T
04
b1z 0
13
0:
11
05
1|
b11001 ,
b11001 -
0~
0{
1}
b110 $
b110 '
#560
1c
1a
0b
1^
0\
b11100 "
b11100 )
b11100 V
0[
b11z W
1Z
09
1X
07
b11001 *
b11001 /
b11001 T
14
b0z 0
03
01
b11000 ,
b11000 -
0|
1{
b111 $
b111 '
#570
1G
1@
0f
0n
1`
1D
0_
0g
0w
1?
0c
0h
0k
0x
1p
0^
18
1a
0b
0i
0t
1q
b1011 "
b1011 )
b1011 V
1[
b0z W
0Z
1<
0\
0d
0P
1l
0X
17
09
0A
0Q
1I
b1000 *
b1000 /
b1000 T
04
b111z 0
13
1:
1B
0M
0J
11
15
1=
0E
1|
1~
1""
b111 ,
b111 -
0$"
0{
0}
0!"
1#"
b1000 $
b1000 '
#580
0q
1n
0l
1g
0I
1k
1i
0G
1f
1d
0@
1_
1A
0D
0a
1b
0?
1^
1\
08
b1010 "
b1010 )
b1010 V
0[
b111z W
1Z
19
0<
1X
07
b111 *
b111 /
b111 T
14
b0z 0
03
01
b110 ,
b110 -
0|
1{
b1001 $
b1001 '
#590
1p
1n
1g
0h
1k
0`
1f
1_
0^
0a
1b
b1001 "
b1001 )
b1001 V
1[
b110z W
0Z
1\
0X
17
19
b110 *
b110 /
b110 T
04
b1z 0
13
0:
11
05
1|
b101 ,
b101 -
0~
0{
1}
b1010 $
b1010 '
#600
1c
1a
0b
1^
0\
b1000 "
b1000 )
b1000 V
0[
b111z W
1Z
09
1X
07
b101 *
b101 /
b101 T
14
b0z 0
03
01
b100 ,
b100 -
0|
1{
b1011 $
b1011 '
#610
0p
0f
0n
1`
0_
0g
1?
0c
1h
0k
0^
18
1a
0b
1i
b111 "
b111 )
b111 V
1[
b0z W
0Z
1<
0\
1d
0X
17
09
1A
b100 *
b100 /
b100 T
04
b11z 0
13
1:
0B
11
15
0=
1|
1~
b11 ,
b11 -
0""
0{
0}
1!"
b1100 $
b1100 '
#620
0i
1f
0d
1_
0A
0a
1b
0?
1^
1\
08
b110 "
b110 )
b110 V
0[
b11z W
1Z
19
0<
1X
07
b11 *
b11 /
b11 T
14
b0z 0
03
01
b10 ,
b10 -
0|
1{
b1101 $
b1101 '
#630
1h
0`
1f
1_
0^
0a
1b
b101 "
b101 )
b101 V
1[
b10z W
0Z
1\
0X
17
19
b10 *
b10 /
b10 T
04
b1z 0
13
0:
11
05
1|
b1 ,
b1 -
0~
0{
1}
b1110 $
b1110 '
#640
1c
1a
0b
1^
0\
b100 "
b100 )
b100 V
0[
b11z W
1Z
09
1X
07
b1 *
b1 /
b1 T
14
b0z 0
03
01
b0 ,
b0 -
0|
1{
b1111 $
b1111 '
#650
1S
1O
x!
1H
0z
1L
0v
1G
0o
1@
0s
1D
0w
1?
0x
18
0j
0t
0q
1<
0\
0d
0P
0l
0p
0X
17
09
0A
1Q
0I
0f
0n
b0 *
b0 /
b0 T
04
b1111z 0
13
1:
1B
1M
1J
0_
0g
11
15
1=
1E
0^
0`
0c
1h
0k
1|
1~
1""
b11111 ,
b11111 -
1$"
b100 "
b100 )
b100 V
0[
b0z W
0Z
0a
1i
0Y
0]
1e
0{
0}
0!"
0#"
b100 +
b100 U
b0 $
b0 '
b100 #
b100 &
#660
1z
1x
1v
1t
x!
1o
1P
0S
1s
1q
0O
1n
1l
0H
0h
b1100z W
1g
1I
0L
0i
1j
0G
1d
0@
1`
1A
0D
1a
0?
1\
08
b11 "
b11 )
b11 V
1[
19
0<
1X
07
b11111 *
b11111 /
b11111 T
14
b0z 0
03
01
b11110 ,
b11110 -
0|
1{
b1 $
b1 '
#670
1`
1a
b10 "
b10 )
b10 V
0[
1\
0X
17
19
b11110 *
b11110 /
b11110 T
04
b1z 0
13
0:
11
05
1|
b11101 ,
b11101 -
0~
0{
1}
b10 $
b10 '
#680
0`
0a
0\
b1 "
b1 )
b1 V
1[
09
1X
07
b11101 *
b11101 /
b11101 T
14
b0z 0
03
01
b11100 ,
b11100 -
0|
1{
b11 $
b11 '
#690
x!
0w
1z
1v
1o
0p
1s
1n
1?
0`
0h
b1100z W
1g
18
0a
0i
1j
b0 "
b0 )
b0 V
0[
1<
0\
1d
0X
17
09
1A
b11100 *
b11100 /
b11100 T
04
b11z 0
13
1:
0B
11
15
0=
1|
1~
b11011 ,
b11011 -
0""
0{
0}
1!"
b100 $
b100 '
#700
0!
1w
0z
0v
0o
1p
0s
0n
1h
b0z W
0g
1i
0j
0d
1`
0A
1a
0?
1\
08
b11111 "
b11111 )
b11111 V
1[
19
0<
1X
07
b11011 *
b11011 /
b11011 T
14
b0z 0
03
01
b11010 ,
b11010 -
0|
1{
b101 $
b101 '
#710
1`
1a
b11110 "
b11110 )
b11110 V
0[
1\
0X
17
19
b11010 *
b11010 /
b11010 T
04
b1z 0
13
0:
11
05
1|
b11001 ,
b11001 -
0~
0{
1}
b110 $
b110 '
#720
0`
0a
0\
b11101 "
b11101 )
b11101 V
1[
09
1X
07
b11001 *
b11001 /
b11001 T
14
b0z 0
03
01
b11000 ,
b11000 -
0|
1{
b111 $
b111 '
#730
1G
1@
1D
0n
0w
1?
0`
1h
b0z W
0g
0x
1p
18
0a
1i
0j
0t
1q
b1100 "
b1100 )
b1100 V
0[
1<
0\
0d
0P
1l
0X
17
09
0A
0Q
1I
b1000 *
b1000 /
b1000 T
04
b111z 0
13
1:
1B
0M
0J
11
15
1=
0E
1|
1~
1""
b111 ,
b111 -
0$"
0{
0}
0!"
1#"
b1000 $
b1000 '
#740
0q
1n
0l
0h
b100z W
1g
0I
0i
1j
0G
1d
0@
1`
1A
0D
1a
0?
1\
08
b1011 "
b1011 )
b1011 V
1[
19
0<
1X
07
b111 *
b111 /
b111 T
14
b0z 0
03
01
b110 ,
b110 -
0|
1{
b1001 $
b1001 '
#750
1`
1a
b1010 "
b1010 )
b1010 V
0[
1\
0X
17
19
b110 *
b110 /
b110 T
04
b1z 0
13
0:
11
05
1|
b101 ,
b101 -
0~
0{
1}
b1010 $
b1010 '
#760
0`
0a
0\
b1001 "
b1001 )
b1001 V
1[
09
1X
07
b101 *
b101 /
b101 T
14
b0z 0
03
01
b100 ,
b100 -
0|
1{
b1011 $
b1011 '
#770
1p
1n
1?
0`
0h
b100z W
1g
18
0a
0i
1j
b1000 "
b1000 )
b1000 V
0[
1<
0\
1d
0X
17
09
1A
b100 *
b100 /
b100 T
04
b11z 0
13
1:
0B
11
15
0=
1|
1~
b11 ,
b11 -
0""
0{
0}
1!"
b1100 $
b1100 '
